Workbook

Sheet 说明
A1: 职业库审查表（2026-10-07 导出）
A3: 数据口径
A4: 抓取样本 3466 条，去重后 2723 条；挂上岗位树 1731 条，未挂上 992 条
A5: 来源：牛企直聘校招单岗页，每个关键词只取搜索第一页；数字是样本数，不是市场岗位数
A6: 单位数 = 挂到该岗位的不同招聘单位数；证据强度：1 家=证据少，2-4 家=一般，5 家及以上=较多
A7: 源文件：/Users/lucky_wang/Documents/codex/xiaogu-career-suite/data/careerdb/（cards.json、edges.json、postings_mapped.jsonl、role_cards/）
A9: 怎么填
A10: 只填黄色列，其余列是库里导出的原始数据，改了不会回写
A11: 岗位审查：逐行看「原始岗位名」是否都属于这个岗位、职责是否对得上，在「审查结论」下拉里选
A12: 样本明细：岗位审查里发现归类问题时，按「挂到的岗位节点」筛选，逐条判断并写「应归到」
A13: 专业连线：判断「这个专业的人去做这个岗位」是否合理
A15: 填写示例（岗位审查）
... A18: 审查进度
A19: 岗位审查：已填结论 | B19: =COUNTA(岗位审查!Q2:Q196) | C19: / 195
A20: 通过 | B20: =COUNTIF(岗位审查!Q2:Q196,"通过")
A21: 归类有误 | B21: =COUNTIF(岗位审查!Q2:Q196,"归类有误")
A22: 应拆分 | B22: =COUNTIF(岗位审查!Q2:Q196,"应拆分")
A23: 应合并 | B23: =COUNTIF(岗位审查!Q2:Q196,"应合并")
A24: 证据不足 | B24: =COUNTIF(岗位审查!Q2:Q196,"证据不足")
A25: 删除 | B25: =COUNTIF(岗位审查!Q2:Q196,"删除")
A26: 待定 | B26: =COUNTIF(岗位审查!Q2:Q196,"待定")
A27: 样本明细：已判断 | B27: =COUNTA(样本明细!M2:M2724) | C27: / 2723
A28: 专业连线：已判断 | B28: =COUNTA(专业连线!J2:J893) | C28: / 892

Sheet 岗位审查
A1: 序号 | B1: 行业 | C1: 类别 | D1: 岗位 | E1: 节点来源 | F1: 优先级 | G1: 样本数 | H1: 单位数 | I1: 证据强度 | J1: 原始岗位名（出现次数） | K1: 学历分布 | L1: 专业分布 | M1: 职责原文（前3条） | N1: 岗位卡阶段 | O1: 岗位卡缺口 | P1: 示例链接 | Q1: 审查结论 | R1: 问题说明 | S1: 修正建议
A2: 1 | B2: 医疗健康 | C2: 医生/医技 | D2: 临床医生（科室未细分） | E2: 招聘样本补充 | G2: 184 | H2: 120 | I2: =IF(H2<2,"证据少",IF(H2<5,"一般","较多")) | J2: 临床医师9、医师5、病理医师5、中医医师4、口腔医师4、临床医生4、精神科医师3、康复医师3、超声医学科医师3、公卫医师3、中医科医师2、保健医生2、精神科医生2、麻醉医生2、中医|针推医生2、兽医师2、医学影像科医师2、临床医学研究员（非实验岗）2、影像医师2、麻醉医师2、营养科医师2、放射诊断科医师2、放射影像科医师1、校招-临床医师（妇产科）（合肥）J536921、耳鼻喉医师-2027届高校毕业生1、临床医学1、眼科住院医生1、临床检验诊断医师1、手术麻醉医师-2027届高校毕业生1、中医科医师(J20530)1、医师|科研岗1、针灸科医生1、中医骨科医师1、康复科医生（2027届）-厦门鹭园1、妇科门诊医师1、心理科医师1、宠物资深医生1、智能医生体验店经营岗集团管培生1、精神科医师（2027年校招）1、2027-超声医师岗(J20983)1、校招-临床医师（耳鼻咽喉科）（北京）J544781、住院医师（27校招岗）1、康复医生1、2027-口腔医师岗(J20984)1、儿科规培医生1、医师岗位|医技岗位|护理岗位|科研岗位|管理岗位及其他专技1、内科执业医生1、临床医师（急诊医学科）（成都）J537071、康复科医生（2027届）-桂园医院1、急诊医学科医师|重症医学科医师1、校招-临床医师（眼科）（成都）J537101、临床医生（2027校招）1、耳鼻咽喉科住院医师(J10840)1、临床医师（重症医学科）（成都）J537021、轻医美大注射医生1、骨科主治医师1、麻醉手术科医师11、2027-病理医师岗(J20979)1、临床医学医师1、整形医生1、麻醉手术科医师21、校招-临床医师（超声医学科）（苏州）J537241、规范化培训住院医师1、医美医师1、内分泌科医师1、耳鼻咽喉科医生1、校招-临床医师（重症医学科）（合肥）J536991、医学影像医师1、2026招聘医师1、全科医疗科医师1、校招-临床医师（心脏大血管外科）（合肥）J536911、核医学中心医师1、重症医学科医师1、康复科医生(J21157)1、全科医学科医师（2027年校招）1、儿科规培医师|儿外科规培医师1、睡眠与脑医学中心医师1、临床医师岗1、妇女保健医师1、校招-临床医师（康复医学科）（成都）J537141、精神科医师11、精神科医师21、口腔医师岗1、预防保健医生1、麻醉手术科医师(J20507)1、耳鼻喉医师1、外科临床医师1、2027-皮肤性病科医师岗(J20974)1、校招-临床医师（妇产科）（北京）J544761、康复医师(J20517)1、康复医学医师1、妇科医师-2027届高校毕业生1、医学影像医生1、中医助理医师1、2027-麻醉医师岗(J20982)1、骨科医生1、影像科住院医师1、校招-临床医师（眼科）（北京）J544771、校招-临床医师（健管中心体检）（合肥）J536901、口腔执业医师（正畸方向）1、临床医师（骨科）（合肥）J536891、麻醉与围术期医学科麻醉医师20271、精神科住院医师1、校招-临床医师（眼科）（合肥）J536951、康复医学科医师1、皮肤性病科医师(J20519)1、宫颈科主治医师1、CCU医生1、超声医学科诊断医师(2027年校招)1、临床医学应届毕业生1、健康管理部医师1、临床医师（放射科）（北京）J544831、兽医师-江西省1、硕士口腔医师1、放射|超声医师岗1、儿科儿保医生（三甲专硕规培）1、精神科医师岗1、临床医师（病理科）（北京）J544821、预防保健科医生1、妇科病房医师1、中医师1、青年医生医助1、皮肤及整形科医师1、2027-影像医师岗(J20981)1、校招-临床医师（麻醉科）（成都）J537131、病理医生1、校招-临床医师（超声科）（合肥）J536971、影像科医生(J21156)1、推拿医生1、烧伤整形科医师(J20511)1、之家-全国-医生1、校招-临床医师（营养科）（北京）J544801、儿科住院医师(J10447)1、精神心理医师1、中医科针推医师1、针灸医生1、2027届应届临床医师1、超声影像科医师1、临床医师（校招）1 | K2: 硕士97、本科46、博士18、未写16、字段与正文不一致7 | L2: 临床医学类104、不限专业15、社会学类15、基础医学类11、口腔医学类10、中医学类9、医学技术类5、公共卫生与预防医学类4、药学类2、护理学类2、教育学类2、中药学类1、工商管理类1、统计学类1 | M2: 住院医师在上级医师指导和授权下，负责日常的诊疗工作 小时内完成住院病历书写 及时了解所管病人每日的病情和体征变化并充分了解检验检查结果 | N2: 未建卡 | P2: https://campus.niuqizp.com/job-v885CZZza.html
A3: 2 | B3: 医疗健康 | C3: 生物医药 | D3: 科研岗（博士后/研究助理） | E3: 招聘样本补充 | F3: P1 | G3: 162 | H3: 149 | I3: =IF(H3<2,"证据少",IF(H3<5,"一般","较多")) | J3: 博士后35、博士后研究人员17、科研助理11、2026招聘博士后人员6、教学科研人员4、博士后研究员3、研究助理3、生物反应器研发科研助理2、专职科研人员2、教学科研2、2026招聘博士后研究人员2、博士后|科研助理2、博士后|副研究员2、分析表征研究助理2、儿科博士后1、生物信息学实验室 AI和数据分析方向的博士后|分子生物学方向的博士后1、运营实习生,职业教育编辑,事业发展部负责人,文字编辑,校对质检编辑,全职营销编辑,实习编辅,版权贸易干事,大众编辑部主任,医学编辑部主任,医学编辑,策划编辑,大众读物编辑室副主任,图书编辑,网络文学编辑,营销编辑,博士后研究人员,翻译研究部研究岗,文化交流部专项工作岗,财务管理部会计岗,当代世界出版社办公室（总编室）,编辑部,发行部,营销宣传部实习岗,人力资源部实习生,编辑运营岗,项目助理实习生,直播助理实习生,高级编辑,编辑助理1、师资博士后1、项目博士后1、生物信息学|数据分析方向博士后1、免疫方向博士后|生物信息学方向博士后|科研助理1、皮肤科治疗技师|影像科技师|骨科生物力学实验室研究助理1、生物智能科研助理1、营养与食品安全方向初级研究助理1、准聘副教授|准聘教授|长聘教授|博士后1、财务处出纳|西餐烹饪工艺教学科研岗|教学秘书1、公文管理助理岗|调查研究助理岗|信息咨政助理岗1、中国古代文学博士后岗位1、科研助理31、博士后-农业生态水文与节水方向1、张永振课题组科研助理1、实验室管理员|分子生物学技术员|生物信息分析师|博士后1、临床|科研型博士后1、肠道菌群方向博士后1、博士后工作站-人工智能在核酸药物开发及应用方向1、医疗大数据挖掘方向博士后1、博士后人员1、水质与水生态研究中心水污染控制的绿色过程方向科研助理51、健康大数据科研助理1、基础医学博士后1、科研人员1、城市人因研究科研助理21、量化与AI应用方向经济学研究助理1、科研助理51、电子源材料与器件研究方向专职科研人员1、人工智能在生物学大数据应用方向博士后研究人员1、2026招聘博士后1、2026招聘中国史博士后岗位1、鲁棒统计学习与因果推断研究方向博士后1、科研型博士后1、AI医学影像博士后1、生物医学工程方向研究助理1、副研究员|助理研究员|博士后|AI|算法工程师1、科研助理岗91、（多模态医学数据分析团队） 博士后1、博士后|实验技术人员|科研助理|项目研究人员1、儿内科临床型博士后1、生物技术学院课题组临床转化研究助理岗位1、生物信息学分析师|科研助理1、乳品微生物|营养与流行病方向科研助理1、科研助理|研究实习员1、临床型博士后|科研型博士后1、分子生物学研究员（博士）/联合博士后1、教研人员|博士后1、教育学博士后研究人员1、比较文学与世界文学博士后岗位1、71名博士后1、创意写作博士后1、管理助理|研究助理1、特别研究助理1、至臻博士后|A类博士后|B类博士后1、中国财政与税收研究所科研助理岗21、临床型博士后1、课题组科研助理21、电子信息材料与器件研究部博士后1、领军人才|学术带头人|优秀副研究员|博士后1、临床前研究助理1、2026招聘教学科研人员1、儿外科临床型博士后1、建筑遗产保护科研助理1、生物医学工程方向博士后1、全职博士后1、博士后岗位（心理学领域）1 | K3: 博士99、本科21、硕士20、未写14、字段与正文不一致7、大专1 | L3: 生物科学类30、计算机类23、基础医学类18、临床医学类17、统计学类13、经济学类11、药学类10、金融学类9、化学类8、心理学类8、社会学类7、新闻传播学类6、教育学类5、建筑类4、管理科学与工程类4、历史学类4、生物医学工程类4、法学类3、工商管理类3、医学技术类3、食品科学与工程类3、中医学类3、不限专业3、公共卫生与预防医学类3、生物工程类2、电子信息类2、电气类2、材料类2、物理学类2、公共管理类2、中国语言文学类2、自动化类2、旅游管理类2、财政学类2、外国语言文学类1、植物生产类1、护理学类1、数学类1、土木类1、环境科学与工程类1、口腔医学类1、机械类1、交通运输类1 | M3: 科研助理（生物反应器研发） 岗位职责 1.积极开展课题设计，完成相关实验、数据分析和论文撰写 完成合作导师交予的其他科研相关事务 | N3: jd_only_draft | O3: 从业者一手分享：未找到可入卡的已核正文，缺2名不同作者 日常体验、考核指标、发展路径与条件化风险：缺从业者证据，不用招聘宣传补齐 未抽出职责句，plain_language与daily_work留空 招聘正文样本不足3：当前0份；联网补抓未执行 可核职责少于4条，不凑数 | P3: https://campus.niuqizp.com/job-v885t5aCC.html
A4: 3 | B4: 教育培训 | C4: 教师 | D4: 教师 | E4: BOSS分类 | F4: P2 | G4: 63 | H4: 48 | I4: =IF(H4<2,"证据少",IF(H4<5,"一般","较多")) | J4: 思政教师5、体育教师5、骨干教师岗位3、教师3、入户早教师2、高等学校教师2、历史教师2、学前教育专业教师2、中草药栽培教师1、小学教育教师1、初高中体育教师1、哲学系外国哲学|中国哲学教师1、教学系列教师1、电气专业教师1、高中政治教师1、2026招聘小学素质类教师1、幼儿部--双语教师、外籍教师1、思想政治理论课教师1、材料科学与工程教师岗位1、计算机专业教师1、幼儿园编制教师1、心理健康教育教师1、法学教师1、学前教育教师1、国际部高中--IGCSE/A-LEVEL 双语（经济、数学、物理、化学、生物）教师1、农业机械化教师1、植物保护教师1、高中体育教师1、园艺教师1、康复训练教师1、早教师1、2026招聘教师1、拔尖人才|青年英才|骨干教师1、高中历史教师1、园林教师1、2026招聘国际中文教师1、2027招聘文科中学授课教师|理科中学授课教师1、技术教师（工作地：海南澄迈）（济南）1、信息工程教师岗位1、大语文|数学思维|双语教师管培生1、中药学教师1、国际中文教育教师1、教师岗位1、旅游管理专业教师1、建筑技术方向教师岗位1、对外汉语教师1、汉语教师 （小班教学 欧美学生）1 | K4: 硕士24、本科14、博士11、未写7、字段与正文不一致5、大专2 | L4: 教育学类14、计算机类6、不限专业5、心理学类5、管理科学与工程类5、体育学类4、中国语言文学类4、法学类3、历史学类3、药学类2、中药学类2、马克思主义理论类2、经济学类2、工商管理类2、化学类1、化工与制药类1、自动化类1、电气类1、材料类1、社会学类1、新闻传播学类1、护理学类1、医学技术类1、外国语言文学类1、音乐与舞蹈学类1、哲学类1、环境科学与工程类1、统计学类1、旅游管理类1、建筑类1 | M4: 教育/培训/院校 培训及其他：配合完成企业培训工作，开发课程方案、课程教学、攻关企业技术难题等 制订教学计划，认真完成日常的备课授课，进行教学总结 | N4: jd_only_draft | O4: 从业者一手分享：未找到可入卡的已核正文，缺2名不同作者 日常体验、考核指标、发展路径与条件化风险：缺从业者证据，不用招聘宣传补齐 | P4: https://campus.niuqizp.com/job-v885CzzM5.html
A5: 4 | B5: 教育培训 | C5: 教师 | D5: 高校教师/辅导员 | E5: 招聘样本补充 | F5: P2 | G5: 45 | H5: 39 | I5: =IF(H5<2,"证据少",IF(H5<5,"一般","较多")) | J5: 教授|副教授|讲师15、专任教师5、讲师3、助理教授|预聘副教授|长聘副教授|教授2、助理教授（教研系列）,助理教授（设计系列）,长聘副教授（教研系列）,准聘副教授或长聘副教授1、储备辅导员岗1、辅导员1、排球|田径|乒乓球|网球教学型讲师1、马克思主义学院专任教师1、商务英语类专任教师1、电子商务类专任教师1、博士专任教师1、学科带头人|教授|副教授|讲师1、汉语言文学|汉语国际教育专任教师1、副教授|讲师1、数据科学与大数据技术专任教师1、教授|副教授|讲师|特聘研究员|特聘副研究员1、重点实验室王志华教授课题组技术员1、助理教授A1、专职辅导员|财务岗1、助理教授|高层次人才1、交叉科学方向统计系教研系列助理教授|副教授|教授1、助理教授|副教授|教授1、思政教师|辅导员1 | K5: 博士33、硕士7、未写3、字段与正文不一致2 | L5: 经济学类7、计算机类7、金融学类3、法学类3、社会学类2、不限专业2、材料类2、建筑类1、动物医学类1、新闻传播学类1、电子信息类1、电气类1、机械类1、统计学类1、工商管理类1、心理学类1、哲学类1、教育学类1、林学类1 | M5: 学院国际化办学特色鲜明，与全球顶尖高校、科研机构建立长期深度合作，国际影响力突出 长聘副教授（教研系列）（城乡规划学）：城乡规划与设计 准聘副教授或长聘副教授（建筑环境与能源应用工程）：建筑能源系统优化设计与智能控制 | N5: jd_only_draft | O5: 从业者一手分享：未找到可入卡的已核正文，缺2名不同作者 日常体验、考核指标、发展路径与条件化风险：缺从业者证据，不用招聘宣传补齐 | P5: https://campus.niuqizp.com/job-v8Y5zaLLn.html
A6: 5 | B6: 医疗健康 | C6: 生物医药 | D6: 医疗产品技术支持 | E6: BOSS分类 | F6: P1 | G6: 41 | H6: 37 | I6: =IF(H6<2,"证据少",IF(H6<5,"一般","较多")) | J6: 应用工程师8、信息化工程师5、临床技术支持专员3、技术支持工程师3、技术支持2、AI应用工程师2、临床技术工程师|临床技术支持专员1、现场应用工程师1、产品技术支持工程师1、医学技术支持1、临床技术支持工程师1、2027届-应用工程师1、大模型应用工程师1、检验线技术支持工程师1、技术支持专员(J12042)1、临床技术支持1、食品技术支持1、仪器应用工程师1、应用工程师（通用）--上海/成都1、项目管理岗|资源开发岗|技术支持岗1、应用工程师-计算光刻（北京）1、IT与AI应用工程师1、开发应用工程师1、无锡区公司-AI应用工程师1 | K6: 本科23、硕士12、未写2、字段与正文不一致2、大专2 | L6: 不限专业11、计算机类6、基础医学类5、临床医学类5、电子信息类4、机械类4、材料类3、化学类3、化工与制药类3、数学类3、物理学类2、医学技术类2、食品科学与工程类2、自动化类2、生物医学工程类1、药学类1、统计学类1、生物工程类1、电气类1、管理科学与工程类1、环境科学与工程类1、教育学类1、生物科学类1、植物生产类1 | M6: 为客户提供化学驱油剂（如聚合物、表面活性剂、碱驱剂等）的应用指导与调试服务 向客户（油田技术团队、作业人员）讲解产品性能、作用机理及操作规范，提供技术培训 收集现场反馈，联动研发团队改进产品配方与应用工艺 | N6: jd_only_draft | O6: 从业者一手分享：未找到可入卡的已核正文，缺2名不同作者 日常体验、考核指标、发展路径与条件化风险：缺从业者证据，不用招聘宣传补齐 | P6: https://campus.niuqizp.com/job-v8U5Nn55z.html
A7: 6 | B7: 人力/行政/法务 | C7: 行政 | D7: 行政专员/助理 | E7: BOSS分类 | F7: P2 | G7: 39 | H7: 35 | I7: =IF(H7<2,"证据少",IF(H7<5,"一般","较多")) | J7: 行政管理岗5、行政管理人员5、行政助理3、生物医学科学行政专员2、宣传公关行政助理1、经济金融及统计类岗位|法律类岗位|财务会计类岗位|综合管理类岗位1、国际教育学院行政管理岗位1、生物学高层次人才培养项目行政助理岗1、医务部行政管理1、教务处培养与专业建设办公室行政管理人员1、综合管理岗1、行政管理专员1、综合管理部后勤保障岗|学术科教部干事岗1、2026招聘工程技术岗|战新产业岗|财务管理岗|外语翻译岗|法律咨询岗|行政管理岗1、综合管理岗|MPA项目综合管理岗1、课题组行政助理1、财税研究所行政管理岗1、行政管理1、综合管理部行政事务岗1、行政管理岗位1、科研行政管理1、教学及学生事务行政专员1、学生行政助理1、综合管理岗位1、行政助理岗1、课题组行政助理岗1、金融财会类岗位|综合管理类岗位1、综合管理岗位01|综合管理岗位02|综合管理岗位03|综合管理岗位041 | K7: 本科20、硕士12、未写4、博士3 | L7: 工商管理类5、生物科学类4、管理科学与工程类4、经济学类3、公共卫生与预防医学类3、计算机类3、金融学类2、不限专业2、中国语言文学类2、法学类2、社会学类2、教育学类2、基础医学类1、临床医学类1、口腔医学类1、中医学类1、药学类1、中药学类1、护理学类1、公共管理类1、土木类1、交通运输类1、马克思主义理论类1、历史学类1 | M7: 完成宣传手册、招生简章、折页等印刷材料的文字编辑与校对 完成上级分配的其他相关任务 负责生物学高层次人才培养项目相关行政事务 | N7: jd_only_draft | O7: 从业者一手分享：未找到可入卡的已核正文，缺2名不同作者 日常体验、考核指标、发展路径与条件化风险：缺从业者证据，不用招聘宣传补齐 | P7: https://campus.niuqizp.com/job-v885zMCNM.html
A8: 7 | B8: 高级管理 | C8: 高级管理职位 | D8: 管理培训生 | E8: 招聘样本补充 | F8: P2 | G8: 36 | H8: 13 | I8: =IF(H8<2,"证据少",IF(H8<5,"一般","较多")) | J8: 物流网络管理培训生2、2027级管理培训生（投资类）1、2027级管理培训生（监察审计类）1、财务管理岗GXZX/管理培训生1、人力资源管理岗ZXLY/管理培训生1、新能源技术监督工程(风电控制方向)JSYJY/管理培训生1、市场营销岗HNSD/管理培训生1、财务管理岗DBSY/管理培训生1、财务管理岗DBXNY/管理培训生1、管理培训生-物流运营1、2027级管理培训生（精算类）1、管理培训生-北苑酒店1、土建管理工程师XJBZ/管理培训生1、2026招聘管理培训生1、热控工程师HZEXB/管理培训生1、安全监督工程师XJXJ/管理培训生1、管理培训生|健康顾问|营养师1、财务管理岗XJXJ/管理培训生1、财务管理岗XJBZ/管理培训生1、人力资源管理岗XJBZ/管理培训生1、总行管理培训生/法律人才专项招聘1、2027级管理培训生（核保核赔类）1、管理培训生-核保方向（所属河北分公司）1、热控工程师XJCN/管理培训生1、财务管理岗HBJJJ/管理培训生1、行政后勤管理岗XJXJ/管理培训生1、集控系统研发工程师JSYJY/管理培训生1、研发技术管理培训生1、人力资源管理岗XJXJ/管理培训生1、综合事务岗XJBZ/管理培训生1、财务管理岗XJCN/管理培训生1、热控工程师DBGC/管理培训生1、管理培训生1、管理培训生-福建分公司1、金融理财顾问方向管理培训生1 | K8: 本科25、硕士11 | L8: 不限专业15、工商管理类6、金融学类3、法学类2、物流管理与工程类2、数学类2、电气类2、能源动力类1、公共管理类1、马克思主义理论类1、新闻传播学类1、计算机类1、环境科学与工程类1、生物工程类1、食品科学与工程类1、电子商务类1、统计学类1、自动化类1、中国语言文学类1、药学类1、心理学类1、经济学类1 | M8: 参与股权投资项目的投前尽调、投后管理和退出工作 协助对子公司战略规划、风险管理和财务等工作提供支持 参与委托投资管理和资产配置执行工作 | N8: jd_only_draft | O8: 从业者一手分享：未找到可入卡的已核正文，缺2名不同作者 日常体验、考核指标、发展路径与条件化风险：缺从业者证据，不用招聘宣传补齐 | P8: https://campus.niuqizp.com/job-v8Y5nLzzt.html
A9: 8 | B9: 医疗健康 | C9: 医疗销售 | D9: 医药代表 | E9: BOSS分类 | F9: P1 | G9: 33 | H9: 25 | I9: =IF(H9<2,"证据少",IF(H9<5,"一般","较多")) | J9: 医药代表8、医学信息沟通专员4、医学信息沟通专员（医药代表）3、医药信息沟通专员2、医学信息沟通管培生1、27届医学信息沟通专员1、2027招聘临床学术专员1、实习医药代表（上海）1、医药代表实习生1、医学信息沟通代表实习生-温州-肠内营养事业部 (MJ000678)1、医学信息沟通代表实习生-台州-肠内营养事业部 (MJ000676)1、医学信息沟通代表实习生-福州-肠内营养事业部 (MJ000679)1、医药代表|学术专员1、医学信息沟通管培生（江西省可分配）1、医学信息沟通代表实习生-宁波-肠内营养事业部 (MJ000677)1、临床代表|医药代表1、医药代表实习生-大连-R28646141、医药代表实习生（扬州）1、医学信息沟通代表实习生-合肥-肠内营养事业部 (MJ000681)1、医学信息沟通代表实习生-盐城-肠内营养事业部 (MJ000680)1 | K9: 本科21、大专8、字段与正文不一致3、未写1 | L9: 不限专业12、药学类12、基础医学类4、临床医学类4、护理学类3、生物工程类2、生物科学类1、化工与制药类1、工商管理类1、食品科学与工程类1 | M9: 负责所在区域的销售工作，与顾客面对面的交谈,介绍产品,让顾客体验产品，完成签单 维护老客户，开拓新市场，发现新客户，拓展业务范围 服从工作安排，配合销售市场部的相关工作 | N9: jd_only_draft | O9: 从业者一手分享：未找到可入卡的已核正文，缺2名不同作者 日常体验、考核指标、发展路径与条件化风险：缺从业者证据，不用招聘宣传补齐 | P9: https://campus.niuqizp.com/job-v8U5MMtNN.html
A10: 9 | B10: 医疗健康 | C10: 医生/医技 | D10: 医学技师（影像/放疗/导管等） | E10: 招聘样本补充 | G10: 32 | H10: 28 | I10: =IF(H10<2,"证据少",IF(H10<5,"一般","较多")) | J10: 检验技师4、生物医学影像技术中心技术人员2、导管室技师2、医学影像科技师2、耳鼻喉科技师|临床科室护理1、医学影像医师/技师1、医学检验科技师1、病理检验医学部检验技师1、放射技师1、康复医学科技师1、现代康复治疗区康复治疗师|传统康复治疗区推拿技师1、康复治疗技师|健康管理师|影像技师|口腔科技师1、前厅技师|前庭方向听力技师1、产后保健科技师|儿童康复科文员|文员1、放射科技师(J10853)1、康复技师（运动康复方向）1、影像技师1、磁共振室影像技师（2027年校招）1、药剂技师1、放射科技师1、前庭方向听力技师|放射技师|药师1、核医学中心技师1、耳鼻喉科技师|社康康复治疗师1、康复治疗师|传统康复治疗区推拿技师1、嗓音耳鼻咽喉头颈外科技师|听力耳鼻咽喉头颈外科技师|口腔科放射技师1、产后康复师|放射影像科技师1 | K10: 本科22、硕士5、博士3、未写2 | L10: 医学技术类18、临床医学类10、基础医学类4、生物医学工程类1、不限专业1、药学类1、化学类1、教育学类1、社会学类1 | M10: 负责医院OCT、AB超、眼底造影等临床医学影像检查与诊断工作 负责医学影像设备的日常维护与保养工作 认真执行各项规章制度和技术操作规程 | N10: 未建卡 | P10: https://campus.niuqizp.com/job-v885Zttnn.html
A11: 10 | B11: 医疗健康 | C11: 护士/护理 | D11: 护士 | E11: BOSS分类 | G11: 30 | H11: 28 | I11: =IF(H11<2,"证据少",IF(H11<5,"一般","较多")) | J11: 护士11、护理4、健康管理护士1、医美护士1、2026招聘护理部护士1、之家-赣园康复医院-护士（27届）1、临床护士1、一年制护士（护理志愿者岗）1、2027届护理应届生1、精神科研究生护理岗1、体检|医美中心护理岗1、护士（27届校招）(J10862)1、护理部护士21、京东体检中心护理岗1、护士/护理（英语）1、临床护士（合肥）J537001、护理部护士11 | K11: 本科14、大专9、未写4、硕士3 | L11: 护理学类22、不限专业4、临床医学类3、社会学类1、环境科学与工程类1 | M11: 负责患者的基础护理与专科护理，密切观察病情变化，及时准确执行医嘱 （1）负责健康管理中心各项护理工作，协助心电图、B超等检查工作 （3）负责体检客户引导、咨询工作，维持体检现场秩序 | N11: 未建卡 | P11: https://campus.niuqizp.com/job-v8U5ZaZMC.html
A12: 11 | B12: 影视/传媒 | C12: 采编/写作/出版 | D12: 编辑 | E12: BOSS分类 | F12: P2 | G12: 26 | H12: 25 | I12: =IF(H12<2,"证据少",IF(H12<5,"一般","较多")) | J12: 编辑7、经济管理类教材学术专著策划编辑3、编辑岗2、实习编辑2、英文数字编辑（外研在线）（2027秋季校招）1、科学编辑1、新闻编辑1、舆情编辑1、英文编辑岗1、Bulletin编辑部 科学编辑1、高起点新刊Transformative Chemistry 科学编辑1、医学SCI文章编辑1、《法学杂志》编辑岗1、图书编辑1、媒体制作技术编辑1、专职编辑1 | K12: 硕士9、博士6、未写5、本科4、字段与正文不一致2 | L12: 新闻传播学类4、统计学类4、金融学类3、财政学类3、外国语言文学类3、数学类3、建筑类2、设计学类2、经济学类2、经济与贸易类2、法学类2、工商管理类2、基础医学类2、临床医学类2、历史学类1、生物科学类1、计算机类1、美术学类1、音乐与舞蹈学类1 | M12: （4）资源维护：开发并维护好跟作者、绘者等合作机构的良好合作关系 有意者请以【应聘实习编辑】应聘者姓名为邮件标题，将简历以附件形式发至 善于沟通，适应团队合作，有责任心、行动力，做事认真、细心，能够整合信息，逻辑缜密 | N12: jd_only_draft | O12: 从业者一手分享：未找到可入卡的已核正文，缺2名不同作者 日常体验、考核指标、发展路径与条件化风险：缺从业者证据，不用招聘宣传补齐 | P12: https://campus.niuqizp.com/job-v8l5ZzLzn.html
A13: 12 | B13: 互联网/AI | C13: 后端开发 | D13: 软件开发工程师（未细分） | E13: 招聘样本补充 | F13: P2 | G13: 25 | H13: 24 | I13: =IF(H13<2,"证据少",IF(H13<5,"一般","较多")) | J13: 软件工程师10、软件开发工程师3、软件开发1、应用软件工程师1、ai软件工程师1、图像处理算法工程师,信号处理算法工程师,AI算法工程师,应用软件工程师,光机结构工程师,电源工程师,嵌入式硬件工程师,产品验证工程师,机械工程师,全球技术支持工程师1、应用软件工程师（地点 武汉）1、软件工程师（地点 武汉）1、信号处理应用软件开发工程师1、软件开发工程师,数据分析师,产品经理,UI,UX设计师,算法工程师,运维工程师,医学内容编辑,客户成功经理,市场推广专员,人力资源专员1、高级高压系统工程师,高级车载能源工程师,高级底盘工程师,高级产品设计工程师,高级CAE工程师,高级车身集成工程师,高级造型设计师,高级整车集成工程师,高级车型成本分析工程师,高级前瞻模具工程师,编程工程师,高级软件工程师1、生物实验工程师|上位机软件工程师1、应用/软件工程师（汽车）1、嵌入式软件工程师1 | K13: 硕士11、本科11、未写3 | L13: 计算机类13、不限专业5、机械类5、自动化类4、材料类4、电气类3、生物医学工程类2、数学类2、统计学类2、物理学类2、基础医学类1、教育学类1、法学类1、管理科学与工程类1、交通运输类1、物流管理与工程类1、工商管理类1、设计学类1、美术学类1、电子信息类1 | M13: 负责项目的软件开发与维护工作 参与项目技术文档的编写工作 参与结构化、高质量数据集建设工作 | N13: jd_only_draft | O13: 从业者一手分享：未找到可入卡的已核正文，缺2名不同作者 日常体验、考核指标、发展路径与条件化风险：缺从业者证据，不用招聘宣传补齐 | P13: https://campus.niuqizp.com/job-v8U5aZ5CN.html
A14: 13 | B14: 生产制造 | C14: 机械设计/制造 | D14: 机械工程师 | E14: BOSS分类 | F14: P2 | G14: 24 | H14: 23 | I14: =IF(H14<2,"证据少",IF(H14<5,"一般","较多")) | J14: 机械设计工程师9、机械工程师6、机械设计2、2027届-机械工程师1、机械设计工程师(J10807)1、机械设计（助理）工程师1、自动化管培生-机械设计方向1、机器人方向机械设计工程师1、机械设计（地点 武汉）1、结构设计工程师|结构设计工程师助理1 | K14: 本科14、硕士7、字段与正文不一致1、大专1、未写1 | L14: 机械类11、不限专业7、设计学类5、自动化类3、电气类2、能源动力类1、计算机类1、土木类1 | M14: 参与机器人集成工作站的需求梳理和结构方案设计 协助完成三维建模、2D工程图输出和BOM选型 参与设备加工装配、测试验证和现场安装调试 | N14: jd_only_draft | O14: 从业者一手分享：未找到可入卡的已核正文，缺2名不同作者 日常体验、考核指标、发展路径与条件化风险：缺从业者证据，不用招聘宣传补齐 | P14: https://campus.niuqizp.com/job-v8m5MCCZn.html
A15: 14 | B15: 互联网/AI | C15: 人工智能 | D15: 算法工程师 | E15: BOSS分类 | F15: P1 | G15: 23 | H15: 20 | I15: =IF(H15<2,"证据少",IF(H15<5,"一般","较多")) | J15: 算法工程师6、图像算法工程师3、图像与图谱算法工程师（地点 宜昌）1、图像处理算法工程师超声,图像处理算法工程师内镜,信号处理算法工程师超声,光学工程师,AI算法工程师,材料开发工程师,临床工程师内镜1、医学研究型PM|医用人工智能算法工程师|转移转化与投资经理1、图像算法工程师（AI）1、研发工程师,实施工程师,算法工程师,数据工程师,产品经理,项目经理,业务顾问,客户经理,销售咨询生1、数学应用算法工程师1、人工智能算法工程师1、图像处理/视觉算法工程师1、深度学习图像算法工程师1、图像处理AI方向算法工程师1、系统算法工程师1、控制算法工程师（博士）1、视觉算法工程师1、应用算法工程师1 | K15: 硕士15、本科3、博士3、字段与正文不一致1、未写1 | L15: 计算机类12、数学类5、不限专业4、基础医学类3、自动化类2、生物医学工程类2、临床医学类1、中医学类1、药学类1、生物科学类1、统计学类1、物理学类1、电子信息类1 | M15: 负责CT图像重建算法的设计、实现与优化，持续提升重建速度和图像质量 负责原始投影数据的预处理、校准和校正，分析并解决伪影及成像异常问题 负责算法的性能测试、评估和工程优化，推动算法在CPU/GPU等平台上的高性能实现 | N15: jd_only_draft | O15: 从业者一手分享：未找到可入卡的已核正文，缺2名不同作者 日常体验、考核指标、发展路径与条件化风险：缺从业者证据，不用招聘宣传补齐 | P15: https://campus.niuqizp.com/job-v8U5nLMZL.html
A16: 15 | B16: 市场/公关/广告 | C16: 市场营销 | D16: 市场营销策划 | E16: BOSS分类 | F16: P2 | G16: 22 | H16: 20 | I16: =IF(H16<2,"证据少",IF(H16<5,"一般","较多")) | J16: 市场专员6、市场营销6、市场营销岗4、市场营销专员2、市场营销经理1、电子商务市场专员1、市场营销实习生1、市场专员（实习）1 | K16: 本科12、未写6、硕士2、字段与正文不一致1、大专1 | L16: 不限专业9、工商管理类5、药学类3、经济与贸易类1、旅游管理类1、设计学类1、基础医学类1、电气类1、公共卫生与预防医学类1、医学技术类1、管理科学与工程类1 | M16: 负责代销机构的对接与维护，参与路演活动，提供渠道业务拓展支持服务 负责直销客户的拓展与维护，对接直销工作相关事宜，完善直销工作流程 与渠道及高净值客户建立长期合作关系， 及时沟通反馈渠道及客户相关问题 | N16: jd_only_draft | O16: 从业者一手分享：未找到可入卡的已核正文，缺2名不同作者 日常体验、考核指标、发展路径与条件化风险：缺从业者证据，不用招聘宣传补齐 | P16: https://campus.niuqizp.com/job-v8Y5ztLNL.html
A17: 16 | B17: 医疗健康 | C17: 临床试验 | D17: 医学事务/医学信息 | E17: 招聘样本补充 | F17: P1 | G17: 22 | H17: 19 | I17: =IF(H17<2,"证据少",IF(H17<5,"一般","较多")) | J17: 医学专员9、真实世界研究业务实习生,医药洞察与咨询分析实习生,ETL实习生,医学运营实习生,大模型算法实习生,大模型应用算法实习生,数据分析实习生,大模型医学产品实习生,商务助理实习生,精细化运营BI实习生,财务BP实习生,人力资源实习生2、（高级）医学专员/产品专员2、医学联络员2、临床技术工程师|医学专业精英|医学联络官|产品岗1、MSL医学联络官1、市场|医学专员1、高级/医学专员1、医学信息专员实习生-广州1、技术支持工程师|医学专员1、医学联络员（MSL)1 | K17: 硕士10、本科9、博士1、字段与正文不一致1、未写1 | L17: 临床医学类13、药学类9、不限专业4、生物医学工程类3、基础医学类2、公共卫生与预防医学类2、生物科学类2、公共管理类2、经济学类2、计算机类2、数学类2、统计学类2、工商管理类2、中医学类1、医学技术类1、护理学类1 | M17: 参与项目初期调研、方案设计阶段相关工作 参与项目申报、监管沟通等相关工作 参与临床实施项目的医学支持工作：方案解读与培训，相关文件撰写，医学沟通等 | N17: jd_plus_scoped_practitioners | O17: 本人分享仅覆盖细分子类：医学事务为MSL，图像算法为CT物理算法；不提升整个混合节点为full | P17: https://campus.niuqizp.com/job-v885NtCMN.html
A18: 17 | B18: 医疗健康 | C18: 医生/医技 | D18: 外科医生 | E18: BOSS分类 | G18: 20 | H18: 18 | I18: =IF(H18<2,"证据少",IF(H18<5,"一般","较多")) | J18: 外科医师8、外科医师岗2、外科医生1、口腔外科医生1、普通外科医师1、耳鼻咽喉头颈外科医师1、2027-普外科医师岗(J20966)1、泌尿外科医师1、外科医师-2027届高校毕业生1、2026招聘外科医生1、神经外科医师助理1、小儿外科医师1 | K18: 硕士13、未写3、本科1、博士1、大专1、字段与正文不一致1 | L18: 临床医学类14、基础医学类3、不限专业1、社会学类1、教育学类1、口腔医学类1 | M18: 负责临床医师日常诊疗及科研工作 严格落实院感防控、医疗核心制度，规范执行各项诊疗操作，杜绝医疗安全隐患 负责外科常见病、多发病的临床诊断、治疗及手术操作，严格执行医疗核心制度 | N18: 未建卡 | P18: https://campus.niuqizp.com/job-v8l5tanaz.html
A19: 18 | B19: 医疗健康 | C19: 医生/医技 | D19: 口腔科医生 | E19: BOSS分类 | G19: 20 | H19: 7 | I19: =IF(H19<2,"证据少",IF(H19<5,"一般","较多")) | J19: 口腔科2、校招-口腔科医师-山东【2027届】1、口腔科医生(J21158)1、校招-口腔科医师-成都【2027届】1、校招-口腔科医师-武汉【2027届】1、口腔科医师1、口腔科医生（2027届）1、校招-口腔科医师-大连【2027届】1、口腔科医师（2027年校招）1、校招-口腔科医师-江苏【2027届】1、口腔科医师(J20508)1、校招-口腔科医师-吉林【2027届】1、校招-口腔科医师-广东【2027届】1、校招-口腔科医师-上海【2027届】1、校招-口腔科医师-昆明【2027届】1、校招-口腔科医师-江西【2027届】1、校招-口腔科医师-浙江【2027届】1、校招-口腔科医师-重庆【2027届】1、校招-口腔科医师-北京【2027届】1 | K19: 本科13、硕士5、大专2 | L19: 口腔医学类18、工商管理类1 | M19: 负责口腔常见病、多发病的诊断与治疗，包括牙体牙髓病、牙周病及简单拔牙等 规范书写门诊病历及医疗文书，确保诊疗记录完整、准确、合规 严格执行无菌操作规范及医院感染控制制度，保障医疗安全 | N19: 未建卡 | P19: https://campus.niuqizp.com/job-v8U5MN5CN.html
A20: 19 | B20: 医疗健康 | C20: 理疗保健 | D20: 营养师/健康管理师 | E20: BOSS分类 | F20: P1 | G20: 20 | H20: 17 | I20: =IF(H20<2,"证据少",IF(H20<5,"一般","较多")) | J20: 健康管理师9、2026招聘健康管理师3、健康管理师|助理健康管理师1、营养师助理1、健康管理师（可实习）1、2026招聘门店健康管理师1、实习营养师——黄山首康1、驻店营养师1、临床营养师1、临床营养师助理1 | K20: 大专13、本科5、未写2 | L20: 基础医学类5、药学类5、不限专业4、护理学类3、医学技术类2、临床医学类2、公共管理类1、公共卫生与预防医学类1、食品科学与工程类1、工商管理类1、中药学类1、社会学类1 | M20: 根据顾客身体情况进行相对应的产品介绍及搭配 跟踪用户健康管理效果，通过数据分析优化服务策略，增强用户粘性 维护客户关系，促进客户满意度和忠诚度 | N20: jd_only_draft | O20: 从业者一手分享：未找到可入卡的已核正文，缺2名不同作者 日常体验、考核指标、发展路径与条件化风险：缺从业者证据，不用招聘宣传补齐 | P20: https://campus.niuqizp.com/job-v885anNMt.html
A21: 20 | B21: 医疗健康 | C21: 临床试验 | D21: 临床监查员 | E21: BOSS分类 | F21: P1 | G21: 19 | H21: 12 | I21: =IF(H21<2,"证据少",IF(H21<5,"一般","较多")) | J21: 临床监查员6、CRA临床监查员3、临床监查员II/III期-厦门 (MJ022455)1、临床监查员II/III期-南京 (MJ022446)1、临床监查员II/III期-南昌 (MJ022436)1、临床监查员II/III期-郑州 (MJ022444)1、临床监查员II/III期-武汉 (MJ022432)1、临床监查员II/III期-长沙 (MJ022434)1、临床监查员CRA（可实习）1、临床监查管培生II/III期-深圳 (MJ022461)1、临床监查员CRA1、临床监查管培生II/III期-郑州 (MJ022452)1 | K21: 本科13、硕士6 | L21: 药学类10、临床医学类8、不限专业8、护理学类5、基础医学类4、中医学类3、公共卫生与预防医学类2、中药学类2、统计学类1、医学技术类1 | M21: 根据公司及部门要求，组织科室宣讲、患者活动以及疾病调查，推进完成项目入组目标 协助研究者完成数据疑问，及时、完整地收集研究相关资料 完成并反馈公司需要收集的各项报告和反馈 | N21: jd_only_draft | O21: 从业者一手分享：未找到可入卡的已核正文，缺2名不同作者 日常体验、考核指标、发展路径与条件化风险：缺从业者证据，不用招聘宣传补齐 | P21: https://campus.niuqizp.com/job-v8r5CaLnZ.html
A22: 21 | B22: 产品 | C22: 产品经理 | D22: 产品经理 | E22: BOSS分类 | F22: P1 | G22: 19 | H22: 19 | I22: =IF(H22<2,"证据少",IF(H22<5,"一般","较多")) | J22: 产品经理12、2026招聘AI应用方向产品经理1、产品经理（校招）1、27届-产品经理1、短期健康保险产品经理1、医学产品经理|医学研究员1、产品经理(J11059)1、生信产品经理1 | K22: 本科12、硕士3、字段与正文不一致2、未写1、博士1 | L22: 计算机类5、不限专业4、电子信息类3、临床医学类3、机械类2、生物科学类2、生物医学工程类2、工商管理类2、自动化类1、医学技术类1、电气类1、管理科学与工程类1、基础医学类1、护理学类1、统计学类1、金融学类1、经济学类1、财政学类1 | M22: 进行用户需求调研和用户行为分析，收集和整理用户反债和数据，为产品设计提供支持 ,参与Ai产品的需求分析、设计和开发工作，协助团队完成产品功能的优化和选代 参与产品选代优化，发现和解决产品中的问题，提高产品质量和用户体验 | N22: jd_only_draft | O22: 从业者一手分享：未找到可入卡的已核正文，缺2名不同作者 日常体验、考核指标、发展路径与条件化风险：缺从业者证据，不用招聘宣传补齐 | P22: https://campus.niuqizp.com/job-v885Cna5n.html
A23: 22 | B23: 医疗健康 | C23: 医生/医技 | D23: 药剂师 | E23: BOSS分类 | G23: 18 | H23: 18 | I23: =IF(H23<2,"证据少",IF(H23<5,"一般","较多")) | J23: 药师4、药剂师3、中药师2、临床药师2、校招-药师（北京）J544891、药师(J10864)1、中药房中药剂师(J21161)1、药剂科药师11、临床护理|药学部药剂师1、药师岗1、药学部中药房中药师1 | K23: 本科10、硕士3、博士3、大专2 | L23: 药学类12、不限专业4、中药学类4、临床医学类1 | M23: 在科主任和上级指导下，从事临床、科研及各项相关工作 日常工作内容：1、负责对药品管理法和医院药品管理制度的严格执行 负责药品的入库、出库管理 | N23: 未建卡 | P23: https://campus.niuqizp.com/job-v885M5ZNZ.html
A24: 23 | B24: 医疗健康 | C24: 生物医药 | D24: 药物分析 | E24: BOSS分类 | F24: P1 | G24: 18 | H24: 13 | I24: =IF(H24<2,"证据少",IF(H24<5,"一般","较多")) | J24: 分析研究员3、药物分析研究员3、化学药生物分析研究员2、药物分析岗1、2027届-生物分析研究员1、生物药生物分析研究员（上海）(J10990)1、受试物分析研究员1、糖类药物分析1、生物药生物分析研究员1、生物药研发工程师/药物分析工程师1、药物分析人员1、分析研究员-本科1、药物分析人员|质量保证人员1 | K24: 硕士9、本科8、字段与正文不一致1 | L24: 药学类13、生物工程类3、生物科学类3、不限专业3、化学类1、法学类1 | M24: 负责生物样本LC-MS/MS方法开发、验证及样品的定量或者半定量分析 分析临床前小分子样本 起草研究报告,包括试验开发、验证、样品分析报告 | N24: jd_only_draft | O24: 从业者一手分享：未找到可入卡的已核正文，缺2名不同作者 日常体验、考核指标、发展路径与条件化风险：缺从业者证据，不用招聘宣传补齐 | P24: https://campus.niuqizp.com/job-v8k5ZNMnn.html
A25: 24 | B25: 医疗健康 | C25: 临床试验 | D25: 临床协调员 | E25: BOSS分类 | F25: P1 | G25: 18 | H25: 13 | I25: =IF(H25<2,"证据少",IF(H25<5,"一般","较多")) | J25: 临床协调员CRC3、临床协调员3、临床研究协调员（CRC）3、临床协调员实习生2、实习临床协调员2、CRC临床协调员|PM项目经理|BD专员1、CRC临床研究协调员1、临床协调员实习生-成都公卫1、2027届临床协调员CRC1、临床协调员实习生-云南省肿瘤医院1 | K25: 本科12、大专6 | L25: 护理学类9、临床医学类8、药学类6、不限专业4、基础医学类1、生物科学类1、工商管理类1、生物工程类1 | M25: 根据GCP和研究方案要求，协助项目负责医生完成临床试验各项非医学判断工作 协助研究者进行试验参与者筛选、入组及随访工作 协助完成文件递交及研究资料的收集、归档和管理工作 | N25: jd_plus_scoped_practitioners | O25: metrics未找到可入卡本人经历证据，留空 | P25: https://campus.niuqizp.com/job-v885nazzz.html
A26: 25 | B26: 电子/电气/通信 | C26: 电气/自动化 | D26: 自动化工程师 | E26: BOSS分类 | F26: P2 | G26: 18 | H26: 17 | I26: =IF(H26<2,"证据少",IF(H26<5,"一般","较多")) | J26: 自动化工程师12、电气与自动化工程师2、自动化工程师（长沙）1、电气自动化工程师（地点 宜昌）1、电气自动化工程师1、2026招聘自动化工程师1 | K26: 本科9、硕士4、未写3、大专2 | L26: 电气类8、自动化类4、机械类4、不限专业3、材料类1、设计学类1 | M26: 新项目导入新产品上线，评估自动化方案 协助设备厂商安装、调试自动化设备 编写设备操作SOP，对产线员工/QC做设备培训 | N26: jd_only_draft | O26: 从业者一手分享：未找到可入卡的已核正文，缺2名不同作者 日常体验、考核指标、发展路径与条件化风险：缺从业者证据，不用招聘宣传补齐 | P26: https://campus.niuqizp.com/job-v885MntCZ.html
A27: 26 | B27: 人力/行政/法务 | C27: 人力资源 | D27: 人力资源专员/助理 | E27: BOSS分类 | F27: P2 | G27: 17 | H27: 16 | I27: =IF(H27<2,"证据少",IF(H27<5,"一般","较多")) | J27: 人力资源岗6、人力资源管理岗3、人力资源管理岗XJXJ1、人力资源管理专员1、人力资源管理1、人力资源管理岗HNSS1、人力资源管理类（哈尔滨）1、人力资源管理职位1、人力资源储备干部（27届）1、人力资源管理师1 | K27: 本科12、硕士4、字段与正文不一致1 | L27: 不限专业10、工商管理类5、公共管理类1、心理学类1、金融学类1 | M27: 协助人力资源规划与制度体系的落地执行 组织实施人力资源模块相关工作，保障人力供给与管理效能 参与搭建可持续的人力资源管理体系，为公司战略提供人才支撑 | N27: jd_only_draft | O27: 从业者一手分享：未找到可入卡的已核正文，缺2名不同作者 日常体验、考核指标、发展路径与条件化风险：缺从业者证据，不用招聘宣传补齐 | P27: https://campus.niuqizp.com/job-v8YNLNZCL.html
A28: 27 | B28: 金融 | C28: 保险 | D28: 保险理赔 | E28: BOSS分类 | F28: P1 | G28: 16 | H28: 13 | I28: =IF(H28<2,"证据少",IF(H28<5,"一般","较多")) | J28: 理赔岗位（车辆保险方向）2、理赔审核岗2、核保数据管培生2、理赔管理岗1、理赔支持岗（包头市本部）1、理赔部理赔管理岗（人伤方向）（所属河北分公司）1、社保理赔岗1、理赔岗（车辆保险方向）1、保险顾问|理赔服务岗1、核保/核赔专员/助理1、理赔类岗位1、理赔管培生1、核保管培生|理赔管培生1 | K28: 本科15、未写1 | L28: 机械类4、不限专业3、金融学类2、交通运输类2、药学类1、生物科学类1、数学类1、物理学类1、土木类1、基础医学类1、法学类1、自动化类1、电气类1、材料类1、动物医学类1、工商管理类1、计算机类1 | M28: 机构理赔数据分析，并制定相应的改善措施 负责理赔规则宣导、问题解释及疑难案件的沟通处理 负责保单基础服务及业务结算、业务续转等工作，统计部门新签协议、投保、续保数据 | N28: jd_only_draft | O28: 从业者一手分享：未找到可入卡的已核正文，缺2名不同作者 日常体验、考核指标、发展路径与条件化风险：缺从业者证据，不用招聘宣传补齐 | P28: https://campus.niuqizp.com/job-v8Y5ZCZZZ.html
A29: 28 | B29: 生产制造 | C29: 质量管理 | D29: 实验室/检测技术员 | E29: 招聘样本补充 | F29: P2 | G29: 16 | H29: 14 | I29: =IF(H29<2,"证据少",IF(H29<5,"一般","较多")) | J29: 实验技术员3、细胞培养实验员2、细胞生物实验员1、27届实验室运营培训生(J15293)1、生物技术实验员1、有源医疗器械检验员|食品业务员1、实验员助理1、毒理实验员1、生物学检验员|新材料及医疗器械业务员1、食品检验员1、化学分析技术员1、研究人员|实验技术员1、光学检验员1 | K29: 本科8、大专3、硕士3、未写1、博士1 | L29: 生物科学类5、药学类4、基础医学类3、临床医学类2、不限专业2、土木类1、生物工程类1 | M29: 负责严格按照SOP的要求进行操作，在工作结束后按照要求完成清场 完成实验任务，提交完整的实验报告，分析存在的问题并及时修正 对本工序的产品质量和工作质量负责 | N29: jd_only_draft | O29: 从业者一手分享：未找到可入卡的已核正文，缺2名不同作者 日常体验、考核指标、发展路径与条件化风险：缺从业者证据，不用招聘宣传补齐 可核职责少于4条，不凑数 | P29: https://campus.niuqizp.com/job-v8U5aZ5tN.html
A30: 29 | B30: 医疗健康 | C30: 医生/医技 | D30: 内科医生 | E30: BOSS分类 | G30: 15 | H30: 14 | I30: =IF(H30<2,"证据少",IF(H30<5,"一般","较多")) | J30: 内科医师4、内科医师岗2、内科医生2、脑血管病内科医师1、呼吸内科医师1、心内科医师1、内科医师-2027届高校毕业生1、心血管内科医师（2027年校招）1、内科医生（2027届）-厦门鹭园1、心血管内科医师1 | K30: 硕士9、本科3、字段与正文不一致2、博士1 | L30: 临床医学类12、社会学类1、不限专业1 | M30: 负责内科常见病、多发病的临床诊断、治疗及病历书写工作，确保医疗文书规范完整 严格执行三级查房制度，参与科室疑难病例讨论与会诊，协助上级医师制定诊疗方案 密切观察患者病情变化，及时处理突发状况，保障医疗安全与质量 | N30: 未建卡 | P30: https://campus.niuqizp.com/job-v8YNL5Lza.html
A31: 30 | B31: 医疗健康 | C31: 医生/医技 | D31: 验光师 | E31: BOSS分类 | G31: 15 | H31: 15 | I31: =IF(H31<2,"证据少",IF(H31<5,"一般","较多")) | J31: 验光师10、2026招聘店员|加工师|验光师1、管培生|储备验光师1、眼镜验光师1、眼科视光师|验光师|儿科评估师1、高级验光师1 | K31: 大专9、本科4、未写2 | L31: 不限专业7、医学技术类2、临床医学类1 | M31: 完成客观、主觉等全流程验光，采集相关信息 开展视功能评估，针对异常给出矫正与训练建议 做好设备日常维保，发现故障及时上报处理 | N31: 未建卡 | P31: https://campus.niuqizp.com/job-v8l5CZnLt.html
A32: 31 | B32: 医疗健康 | C32: 医生/医技 | D32: 医生助理 | E32: BOSS分类 | G32: 14 | H32: 14 | I32: =IF(H32<2,"证据少",IF(H32<5,"一般","较多")) | J32: 医生助理6、医疗助理5、医师助理1、医疗助理员1、宠物医生助理1 | K32: 本科8、大专5、未写1 | L32: 基础医学类5、临床医学类4、医学技术类2、中医学类1、公共管理类1、动物医学类1、护理学类1、不限专业1 | M32: 负责专家的日常沟通服务，确保专家出诊的后勤保障工作 收集专家出诊期间的相关需求，并跟进落实 负责医院住院患者的随访工作 | N32: 未建卡 | P32: https://campus.niuqizp.com/job-v8y5tzC5n.html
A33: 32 | B33: 医疗健康 | C33: 生物医药 | D33: 制剂研发 | E33: BOSS分类 | F33: P1 | G33: 14 | H33: 12 | I33: =IF(H33<2,"证据少",IF(H33<5,"一般","较多")) | J33: 制剂研究员5、制剂研发员2、外用制剂开发研究员1、制剂开发科学家1、制剂研发1、药物制剂研发1、中药制剂开发研究员1、化药药物制剂研发1、制剂开发工程师1 | K33: 硕士5、博士4、字段与正文不一致2、本科2、未写1 | L33: 药学类4、不限专业3、生物科学类2、化工与制药类2、机械类1、生物工程类1 | M33: 负责项目工艺研究，包括处方筛选、工艺优化、包材选择、稳定性考察等 完成上级领导交办的其它工作 进行处方筛选与工艺优化，确保制剂的稳定性、生物利用度和可放大性 | N33: jd_only_draft | O33: 从业者一手分享：未找到可入卡的已核正文，缺2名不同作者 日常体验、考核指标、发展路径与条件化风险：缺从业者证据，不用招聘宣传补齐 | P33: https://campus.niuqizp.com/job-v8Y5CatM5.html
A34: 33 | B34: 医疗健康 | C34: 医疗销售 | D34: 健康顾问 | E34: BOSS分类 | F34: P1 | G34: 14 | H34: 14 | I34: =IF(H34<2,"证据少",IF(H34<5,"一般","较多")) | J34: 健康顾问9、口腔健康顾问1、产品健康顾问1、健康顾问（免费住宿、晋升空间大）1、中医健康顾问1、前台咨询|研发助理|健康顾问|市场运营1 | K34: 大专11、未写2、本科1 | L34: 不限专业5、护理学类5、药学类4、医学技术类4、食品科学与工程类3、公共卫生与预防医学类2、临床医学类2、中医学类2、工商管理类1、电子商务类1 | M34: 岗位职责1、负责到店客户接待、健康咨询服务 协调、确定治疗方案，达成患者转化、成交 对于未成交患者，和患者讨论该方案的好处和潜在未治疗，并跟进回访 | N34: jd_only_draft | O34: 从业者一手分享：未找到可入卡的已核正文，缺2名不同作者 日常体验、考核指标、发展路径与条件化风险：缺从业者证据，不用招聘宣传补齐 | P34: https://campus.niuqizp.com/job-v8lNLZazC.html
A35: 34 | B35: 医疗健康 | C35: 生物医药 | D35: 药物合成 | E35: BOSS分类 | F35: P1 | G35: 13 | H35: 11 | I35: =IF(H35<2,"证据少",IF(H35<5,"一般","较多")) | J35: 合成研究员4、药化合成研究员3、有机合成研究员2、初级合成研究员1、化学合成研究员1、药物合成工作人员1、药物合成分析研究员1 | K35: 硕士9、本科2、博士1、字段与正文不一致1 | L35: 药学类6、化工与制药类3、不限专业2、化学类1、材料类1 | M35: 从事药物合成相关工作，协助有机合成化合物的研发 按要求进行实验记录以及独立分析、解决实验问题 完成公司研发项目及订单生产 | N35: jd_only_draft | O35: 从业者一手分享：未找到可入卡的已核正文，缺2名不同作者 日常体验、考核指标、发展路径与条件化风险：缺从业者证据，不用招聘宣传补齐 | P35: https://campus.niuqizp.com/job-v885MLCzC.html
A36: 35 | B36: 互联网/AI | C36: 技术项目管理 | D36: 项目经理/主管 | E36: BOSS分类 | F36: P2 | G36: 13 | H36: 11 | I36: =IF(H36<2,"证据少",IF(H36<5,"一般","较多")) | J36: 生产项目经理2、项目经理1、石嘴山分公司-项目经理1、东莞分公司-项目经理1、公共绩效与信息化研究中心项目主管1、项目经理（2027届校招）1、项目主管,见习生,项目实习生,传播实习生,行政实习生,社工服务站主任,社工服务站副主任,社工服务站片长,社工服务站一线社工,社工服务站社工助理1、项目主管岗位1、项目经理(英语/日语/韩语)1、研发项目经理1、医药客户项目经理1、项目经理（商务人员）1 | K36: 本科5、博士3、硕士3、大专1、未写1 | L36: 不限专业4、临床医学类2、药学类2、经济学类1、统计学类1、心理学类1、公共管理类1、社会学类1、新闻传播学类1、公共卫生与预防医学类1、化学类1、工商管理类1、基础医学类1 | M36: 负责研发项目全周期管理，统筹规划、执行与跟踪，保障项目按期推进 协调内外部资源，跟进原料药合成、制剂、质量研究进度，汇总项目数据 参与技术转移、工艺优化，协助 CTD 等申报资料整理撰写 | N36: jd_only_draft | O36: 从业者一手分享：未找到可入卡的已核正文，缺2名不同作者 日常体验、考核指标、发展路径与条件化风险：缺从业者证据，不用招聘宣传补齐 | P36: https://campus.niuqizp.com/job-vU85Caa5t.html
A37: 36 | B37: 客服/运营 | C37: 内容运营 | D37: 新媒体运营 | E37: BOSS分类 | F37: P2 | G37: 13 | H37: 13 | I37: =IF(H37<2,"证据少",IF(H37<5,"一般","较多")) | J37: 新媒体运营7、新媒体运营实习编辑,研究员助理实习生2、社交媒体部新媒体运营实习生1、文科教师|理科教师|教育主播|新媒体运营专员1、新媒体运营实习生1、网络新媒体运营1 | K37: 本科10、大专2、未写1 | L37: 不限专业4、新闻传播学类3、经济学类2、法学类2、社会学类2、戏剧与影视学类2、心理学类1、历史学类1、中国语言文学类1、计算机类1、设计学类1、美术学类1、音乐与舞蹈学类1、工商管理类1 | M37: 岗位职责：撰写策划方案，协助新媒体产品制作，支持重点项目 统筹视频更新、政策更新、意向用户线索跟进等多项任务，确保工作节奏有序、不遗漏 研究员助理实习生（2 - 4名）：协助研究员进行课题的资料收集等基础研究工作 | N37: jd_only_draft | O37: 从业者一手分享：未找到可入卡的已核正文，缺2名不同作者 日常体验、考核指标、发展路径与条件化风险：缺从业者证据，不用招聘宣传补齐 | P37: https://campus.niuqizp.com/job-v885ztNZa.html
A38: 37 | B38: 教育培训 | C38: 教师 | D38: 英语教师 | E38: BOSS分类 | F38: P2 | G38: 13 | H38: 12 | I38: =IF(H38<2,"证据少",IF(H38<5,"一般","较多")) | J38: 英语老师4、英语教师4、双语小学部、初中--双语数学教师、英语教师、外籍教师1、青少英语教师(国际教育)1、小学英语老师1、小学部--语文教师、数学教师、英语教师、外籍教师1、小学英语教师1 | K38: 本科11、硕士2 | L38: 不限专业7、外国语言文学类1 | M38: 外籍教师注重营造真实语言环境，参与英语活动、课程开发与资源建设 参与教研、集体备课、听课评课、命题评估、教学质量分析及课程资源建设 关注学生个体差异，做好学习指导、习惯培养与家校沟通，配合班级管理及学校活动 | N38: jd_only_draft | O38: 从业者一手分享：未找到可入卡的已核正文，缺2名不同作者 日常体验、考核指标、发展路径与条件化风险：缺从业者证据，不用招聘宣传补齐 | P38: https://campus.niuqizp.com/job-v8UNLNMCC.html
A39: 38 | B39: 房地产/建筑 | C39: 工程管理 | D39: 工程造价 | E39: BOSS分类 | F39: P2 | G39: 13 | H39: 10 | I39: =IF(H39<2,"证据少",IF(H39<5,"一般","较多")) | J39: 工程造价-园林古建工程1、工程造价师1、工程造价咨询工程师-乌鲁木齐1、工程造价工程师1、工程造价岗1、水务-工程造价1、电力工程造价员1、工程造价1、工程造价工程技术人员1、工程造价-北京1、工程造价-上海1、工程造价专员1、工程造价岗-城建一公司1 | K39: 本科10、硕士2、大专1 | L39: 不限专业6、管理科学与工程类5、电气类1 | M39: 岗位职责： 1、承担项目成本分析，保证项目收益，管理项目工程量计算、预算报价 参与项目合同的谈判、评审、签订与交底，合理转移总包风险 负责项目经营报价、进度款审核、结算及工程竣工结算 | N39: jd_only_draft | O39: 从业者一手分享：未找到可入卡的已核正文，缺2名不同作者 日常体验、考核指标、发展路径与条件化风险：缺从业者证据，不用招聘宣传补齐 | P39: https://campus.niuqizp.com/job-vYm5ananM.html
A40: 39 | B40: 医疗健康 | C40: 医生/医技 | D40: 皮肤科医生 | E40: BOSS分类 | G40: 12 | H40: 12 | I40: =IF(H40<2,"证据少",IF(H40<5,"一般","较多")) | J40: 皮肤科医师2、皮肤科2、皮肤科住院医师(J10855)1、皮肤科医师（医美部）医师1、皮肤科医生1、皮肤科住院医师1、皮肤科医生(J21159)1、2027招聘皮肤科医师1、皮肤科中西医结合医师1、皮肤科医师（2027年校招）1 | K40: 硕士8、博士2、未写2 | L40: 临床医学类9、社会学类1、不限专业1、中医学类1 | M40: 在科主任领导和主治医师指导下对病患进行检查、诊断、治疗，开写医嘱并检查其执行情况 负责书写病患住院期间的病程记录，及时完成出院病员的病案小结 向主治医师及时报告诊断、治疗上的困难以及病患病情的变化，提出需要转科或出院的意见 | N40: 未建卡 | P40: https://campus.niuqizp.com/job-vUm5MZCza.html
A41: 40 | B41: 医疗健康 | C41: 医生/医技 | D41: 眼科医生 | E41: BOSS分类 | G41: 12 | H41: 12 | I41: =IF(H41<2,"证据少",IF(H41<5,"一般","较多")) | J41: 眼科医生5、眼科医师3、眼科医生（2027届）1、眼科医师（2027年校招）1、眼科医师-2027届高校毕业生1、2027-眼科医师岗(J20977)1 | K41: 硕士5、博士4、未写1、本科1、字段与正文不一致1 | L41: 临床医学类5 | M41: 在科主任领导和上级医师指导下，负责科室一定范围的医疗、科研工作 按时查房，进行诊断、治疗及特殊诊疗操作，参加值班、门诊、会诊、出诊工作 负责门诊患者诊疗工作 | N41: 未建卡 | P41: https://campus.niuqizp.com/job-v8yNL5LaM.html
A42: 41 | B42: 医疗健康 | C42: 医生/医技 | D42: 全科医生 | E42: BOSS分类 | G42: 12 | H42: 9 | I42: =IF(H42<2,"证据少",IF(H42<5,"一般","较多")) | J42: 全科医生2、全科医师2、全科医师岗2、全科医生-泰康之家·冀园1、综合门诊|全科医生1、全科医生助理1、临床-全科医师1、全科医生（2027届）-厦门鹭园1、2027-全科医师岗(J20963)1 | K42: 硕士7、本科4、字段与正文不一致1 | L42: 临床医学类9、中医学类1、不限专业1、基础医学类1 | M42: 负责社区患者常见病、多发病诊疗工作 建立并管理慢性病患者健康档案，办理家庭医生签约手续 根据病情需要，及时、准确地将患者转诊至上级医院或专科医生，并协助患者完成转诊流程 | N42: 未建卡 | P42: https://campus.niuqizp.com/job-vU85tnz5z.html
A43: 42 | B43: 财务/审计/税务 | C43: 会计 | D43: 会计 | E43: BOSS分类 | F43: P2 | G43: 12 | H43: 12 | I43: =IF(H43<2,"证据少",IF(H43<5,"一般","较多")) | J43: 会计6、税务会计2、办公室会计岗1、会计实习生1、会计岗位1、会计岗1 | K43: 本科6、大专2、未写2、硕士2 | L43: 不限专业4、工商管理类4、金融学类1、经济学类1、财政学类1、材料类1 | M43: 准确核算各类税费，按时完成纳税申报、税款缴纳及退税办理 整理归档税务相关凭证、报表，建立健全税务台账 对接税务机关，配合税务稽查与专项检查，处理涉税咨询 | N43: jd_only_draft | O43: 从业者一手分享：未找到可入卡的已核正文，缺2名不同作者 日常体验、考核指标、发展路径与条件化风险：缺从业者证据，不用招聘宣传补齐 | P43: https://campus.niuqizp.com/job-v8Y5ztnnC.html
A44: 43 | B44: 影视/传媒 | C44: 采编/写作/出版 | D44: 期刊/学术编辑 | E44: 招聘样本补充 | F44: P1 | G44: 12 | H44: 9 | I44: =IF(H44<2,"证据少",IF(H44<5,"一般","较多")) | J44: 学术编辑2、英文期刊编辑2、生物医学工程学院国际高水平英文期刊编辑1、期刊编辑|编务1、医学英文期刊编辑1、期刊编辑岗1、审计岗|编辑岗|期刊编辑岗|数字产品经理岗|终审编辑岗1、期刊编辑人员1、英文医学期刊编辑1、期刊编辑/编务1 | K44: 硕士7、本科4、博士1 | L44: 临床医学类2、基础医学类2、交通运输类2、计算机类2、生物医学工程类1、口腔医学类1、药学类1、经济学类1、新闻传播学类1、历史学类1、电气类1、机械类1、材料类1、环境科学与工程类1、物理学类1、工商管理类1、设计学类1、中国语言文学类1 | M44: 生物医学工程学院国际高水平英文期刊编辑1名 参与期刊国际合作洽谈、核心数据库收录申报等工作，全面提升期刊国际影响力 工资和各项福利待遇按照国家及信息所有关政策执行 | N44: jd_only_draft | O44: 从业者一手分享：未找到可入卡的已核正文，缺2名不同作者 日常体验、考核指标、发展路径与条件化风险：缺从业者证据，不用招聘宣传补齐 | P44: https://campus.niuqizp.com/job-vUr5ZCNNt.html
A45: 44 | B45: 互联网/AI | C45: 运维/技术支持 | D45: 信息安全工程师 | E45: 招聘样本补充 | F45: P2 | G45: 12 | H45: 11 | I45: =IF(H45<2,"证据少",IF(H45<5,"一般","较多")) | J45: 信息安全工程师5、信息安全及数据管理2、茂名分公司-信息安全运营1、信息安全工程师-流程IT与质量（27届）1、信息安全岗1、开发|测试|信息安全|系统运维类1、信息安全架构工程师1 | K45: 本科9、字段与正文不一致2、未写1 | L45: 计算机类10、不限专业2、电子信息类1、自动化类1、机械类1 | M45: 【岗位职责】 1、参与公司信息安全体系的日常运维工作，学习安全策略与管理制度 协助完成漏洞扫描与修复跟踪，参与风险评估的基础工作，逐步接触渗透测试 参与安全事件的监测与响应流程，学习事件分析的基本方法论，协助编写报告 | N45: jd_only_draft | O45: 从业者一手分享：未找到可入卡的已核正文，缺2名不同作者 日常体验、考核指标、发展路径与条件化风险：缺从业者证据，不用招聘宣传补齐 | P45: https://campus.niuqizp.com/job-v8Y5MLzt5.html
A46: 45 | B46: 医疗健康 | C46: 医生/医技 | D46: 麻醉科医生 | E46: BOSS分类 | G46: 11 | H46: 11 | I46: =IF(H46<2,"证据少",IF(H46<5,"一般","较多")) | J46: 麻醉科医师7、麻醉科医生3、麻醉科医师岗1 | K46: 硕士7、未写2、字段与正文不一致1、本科1 | L46: 临床医学类10、社会学类2、基础医学类1 | M46: 在科主任领导下和上级医师指导下，负责本科的日常麻醉、教学、科研的具体工作 手术后进行随访，将有关情况记入术后随访记录单，并做好麻醉总结 遇疑难病例不能单独处理时，应及时报告上级医师 | N46: 未建卡 | P46: https://campus.niuqizp.com/job-v8855aanN.html
A47: 46 | B47: 医疗健康 | C47: 理疗保健 | D47: 康复治疗师 | E47: BOSS分类 | F47: P1 | G47: 11 | H47: 10 | I47: =IF(H47<2,"证据少",IF(H47<5,"一般","较多")) | J47: 康复治疗师4、特教康复治疗师1、儿童康复治疗师1、运动康复治疗师1、康复治疗师（儿康）1、康复治疗师（2027届）-厦门鹭园1、康复治疗师【苏康养老年病医院】1、康复治疗-27届校招-楚园（武汉）1 | K47: 本科4、大专3、未写2、硕士2 | L47: 医学技术类6、基础医学类3、临床医学类2、社会学类2、体育学类2、心理学类1、教育学类1、管理科学与工程类1 | M47: 制定教学计划及教学方案 做好与家长沟通工作并及时反馈家长意见 协助教学主任做好教学工作 | N47: jd_only_draft | O47: 从业者一手分享：未找到可入卡的已核正文，缺2名不同作者 日常体验、考核指标、发展路径与条件化风险：缺从业者证据，不用招聘宣传补齐 | P47: https://campus.niuqizp.com/job-v8y5tMnLL.html
A48: 47 | B48: 医疗健康 | C48: 生物医药 | D48: 药物警戒 | E48: 招聘样本补充 | F48: P1 | G48: 11 | H48: 9 | I48: =IF(H48<2,"证据少",IF(H48<5,"一般","较多")) | J48: 药物警戒专员8、药物警戒校招实习2、2026招聘日韩药物警戒1 | K48: 本科6、硕士5 | L48: 药学类4、护理学类2、统计学类1、临床医学类1、不限专业1、公共卫生与预防医学类1、基础医学类1、中医学类1、中药学类1、生物科学类1、外国语言文学类1 | M48: ? 安全性数据汇总分析与报告 ? 安全性数据库维护 ? 药物警戒相关法规的学习和跟进 | N48: jd_plus_scoped_practitioners | O48: growth未找到可入卡本人经历证据，留空 | P48: https://campus.niuqizp.com/job-vUr5tt5zt.html
A49: 48 | B49: 互联网/AI | C49: 人工智能 | D49: 医学AI/生物医学大模型 | E49: 招聘样本补充 | F49: P1 | G49: 11 | H49: 9 | I49: =IF(H49<2,"证据少",IF(H49<5,"一般","较多")) | J49: AI医疗反向工程师1、AIDD科学家1、AI化学高级研究员1、制药知识AI应用推广专员1、2027届-AIDD研究员1、医学人工智能临床复合型医师|医学数据治理工程师|医学智能体工程师1、制药知识AI应用研究员1、AI医疗行业—数据标注实习生1、AI医疗大模型应用开发实习生1、AIDD研究员1、生物医学大模型研发1 | K49: 硕士5、博士2、本科2、字段与正文不一致1、未写1 | L49: 药学类5、计算机类3、不限专业3、生物科学类2、基础医学类2、化学类2、生物医学工程类2、临床医学类1 | M49: 负责肿瘤方向的AIDD（人工智能药物设计）研发工作 开展大分子与小分子药物的相关研究，推动项目进展与技术突破 利用AI与计算工具优化药物分子结构，提升研发效率 | N49: jd_only_draft | O49: 从业者一手分享：未找到可入卡的已核正文，缺2名不同作者 日常体验、考核指标、发展路径与条件化风险：缺从业者证据，不用招聘宣传补齐 | P49: https://campus.niuqizp.com/job-v8Y5na5NZ.html
A50: 49 | B50: 医疗健康 | C50: 医生/医技 | D50: 儿科医生 | E50: BOSS分类 | G50: 10 | H50: 10 | I50: =IF(H50<2,"证据少",IF(H50<5,"一般","较多")) | J50: 儿科医师4、儿科医生2、儿科医生（三甲医院）1、儿科医师岗1、2027-儿科医师岗(J20965)1、儿科医师（2027年校招）1 | K50: 硕士7、本科2、博士1 | L50: 临床医学类9、社会学类1 | M50: 负责临床医师日常诊疗及科研工作 负责儿科常见病、多发病的筛查、诊断与规范化临床诊疗工作，落实常规临床诊疗业务 严格按照医疗规范及质控标准书写各类医疗文书，规范完成病历撰写、治疗方案制定等工作 | N50: 未建卡 | P50: https://campus.niuqizp.com/job-v8s5CanNz.html
A51: 50 | B51: 医疗健康 | C51: 医生/医技 | D51: 放射科医生 | E51: BOSS分类 | G51: 10 | H51: 10 | I51: =IF(H51<2,"证据少",IF(H51<5,"一般","较多")) | J51: 放射科医师5、放射科诊断医师1、放射科影像诊断医师1、放射科医生1、放射科住院医师(J10852)1、放射科诊断医生1 | K51: 硕士6、本科2、未写1、字段与正文不一致1 | L51: 临床医学类8、基础医学类2、社会学类1、不限专业1 | M51: 负责放射科常规X线、CT及MRI等影像资料的诊断工作，出具准确、规范的诊断报告 参与科室疑难病例讨论与会诊，协助临床医师制定诊疗方案，确保医疗质量与安全 严格遵守放射防护规定及设备操作规程，配合完成科室教学、科研及公共卫生任务 | N51: 未建卡 | P51: https://campus.niuqizp.com/job-vUU5nLZNM.html
A52: 51 | B52: 医疗健康 | C52: 理疗保健 | D52: 理疗师 | E52: BOSS分类 | F52: P1 | G52: 10 | H52: 9 | I52: =IF(H52<2,"证据少",IF(H52<5,"一般","较多")) | J52: 康复理疗师5、理疗师3、中医康复理疗师1、中医理疗师1 | K52: 大专7、本科2、未写1 | L52: 社会学类3、医学技术类2、中医学类1、护理学类1、不限专业1、基础医学类1 | M52: 运用理疗技术进行日常调理与康复支持 维护理疗过程的安全性与服务质量 配合健康管理团队完成相关记录与反馈 | N52: jd_only_draft | O52: 从业者一手分享：未找到可入卡的已核正文，缺2名不同作者 日常体验、考核指标、发展路径与条件化风险：缺从业者证据，不用招聘宣传补齐 | P52: https://campus.niuqizp.com/job-vUr5aMNML.html
A53: 52 | B53: 医疗健康 | C53: 生物医药 | D53: 生物信息工程师 | E53: BOSS分类 | F53: P1 | G53: 10 | H53: 10 | I53: =IF(H53<2,"证据少",IF(H53<5,"一般","较多")) | J53: 生物信息工程师4、Teschendorff研究组 计算生物学实验室助理1、生物信息分析工程师1、生物信息学分析工程师1、AI生物信息工程师1、生物信息开发工程师1、生物信息分析专员|医学销售1 | K53: 本科5、硕士3、字段与正文不一致1、博士1 | L53: 生物科学类4、计算机类3、不限专业2、统计学类1、生物医学工程类1 | M53: 实验室助理将负责日常实验室管理工作，包括外国学生的管理等 实验室助理将协助实验室财务（会计）事宜、组织会议、出差安排以及文件的英中互译 对毕业生而言，这是一个在学术界进行职业发展和提升英语沟通技能的绝佳机会 | N53: jd_only_draft | O53: 从业者一手分享：未找到可入卡的已核正文，缺2名不同作者 日常体验、考核指标、发展路径与条件化风险：缺从业者证据，不用招聘宣传补齐 | P53: https://campus.niuqizp.com/job-vU85NCNZt.html
A54: 53 | B54: 医疗健康 | C54: 生物医药 | D54: 药品注册 | E54: BOSS分类 | F54: P1 | G54: 10 | H54: 9 | I54: =IF(H54<2,"证据少",IF(H54<5,"一般","较多")) | J54: 药品注册专员3、注册专员3、临床注册专员1、国内/国际注册专员1、药品注册1、医疗器械海外注册专员1 | K54: 本科6、硕士4 | L54: 药学类7、基础医学类2、临床医学类2、生物医学工程类2、化学类2、公共卫生与预防医学类1 | M54: 负责与产品有关的相关法规及标准的收集，并根据体系要求进行控制 协助与其他部门工作上的协调沟通 负责与境外药企沟通，收集符合国家药品监督管理局注册要求的DMF文件 | N54: jd_only_draft | O54: 从业者一手分享：未找到可入卡的已核正文，缺2名不同作者 日常体验、考核指标、发展路径与条件化风险：缺从业者证据，不用招聘宣传补齐 | P54: https://campus.niuqizp.com/job-vUm5taMnN.html
A55: 54 | B55: 互联网/AI | C55: 人工智能 | D55: 数据标注/AI训练师 | E55: BOSS分类 | F55: P1 | G55: 10 | H55: 8 | I55: =IF(H55<2,"证据少",IF(H55<5,"一般","较多")) | J55: 数据标注师3、数据标注员3、AI数据标注1、音乐标注项目-数据标注1、数据标注1、数据标注师AI训练师1 | K55: 大专3、本科3、字段与正文不一致2、未写2 | L55: 计算机类6、不限专业2、心理学类1、电子信息类1、戏剧与影视学类1、音乐与舞蹈学类1、法学类1 | M55: 参与评测数据集的构建、整理与迭代，保证覆盖全面、场景真实、可持续更新 参与评估方案、评估规则的制定、落实与持续优化 收集并整理评测过程中的问题与歧义，推动规则更新迭代，提升规则的覆盖性与适用性 | N55: jd_only_draft | O55: 从业者一手分享：未找到可入卡的已核正文，缺2名不同作者 日常体验、考核指标、发展路径与条件化风险：缺从业者证据，不用招聘宣传补齐 | P55: https://campus.niuqizp.com/job-vUm55MtZC.html
A56: 55 | B56: 医疗健康 | C56: 护士/护理 | D56: 护工 | E56: BOSS分类 | G56: 9 | H56: 9 | I56: =IF(H56<2,"证据少",IF(H56<5,"一般","较多")) | J56: 照护师7、医疗护理员1、护工1 | K56: 大专9 | L56: 护理学类6、公共卫生与预防医学类1 | M56: 在护士的指导下，负责为长者提供服药等规定范围内的照护服务 负责正确使用生活 辅助设备、器械，辅助长者进行功能训练 协助长者急症抢救工作，配合处理长者突发健康事件 | N56: 未建卡 | P56: https://campus.niuqizp.com/job-v8k5CanLZ.html
A57: 56 | B57: 医疗健康 | C57: 其他医疗健康职位 | D57: 医学编辑 | E57: BOSS分类 | F57: P1 | G57: 9 | H57: 9 | I57: =IF(H57<2,"证据少",IF(H57<5,"一般","较多")) | J57: 医学编辑5、医学出版中心负责人,医学编辑,综合编辑,发行部负责人,实习生,新媒体实习生1、医学编辑|生物医学编辑1、生产监查员|医学编辑1、药学方向医学编辑|医学编辑1 | K57: 本科8、硕士1 | L57: 临床医学类5、药学类4、医学技术类3、中国语言文学类1、外国语言文学类1、不限专业1、口腔医学类1、基础医学类1、护理学类1、中医学类1 | M57: 对出版图书导向与质量负责 负责编辑人员的业务培训工作、编辑队伍建设工作 完成公司布置的其他工作 | N57: jd_only_draft | O57: 从业者一手分享：未找到可入卡的已核正文，缺2名不同作者 日常体验、考核指标、发展路径与条件化风险：缺从业者证据，不用招聘宣传补齐 未抽出职责句，plain_language与daily_work留空 招聘正文样本不足3：当前2份；联网补抓未执行 可核职责少于4条，不凑数 | P57: https://campus.niuqizp.com/job-vmm5ZzZMZ.html
A58: 57 | B58: 医疗健康 | C58: 医生/医技 | D58: 耳鼻喉科医生 | E58: BOSS分类 | G58: 8 | H58: 8 | I58: =IF(H58<2,"证据少",IF(H58<5,"一般","较多")) | J58: 耳鼻喉科3、耳鼻喉科医师2、耳鼻喉科医生1、耳鼻喉科医师（2027年校招）1、耳鼻喉科医生（2027届）1 | K58: 硕士5、字段与正文不一致1、大专1、博士1 | L58: 临床医学类2、社会学类1、基础医学类1、不限专业1 | M58: 严格按照医疗规范书写各类医疗文书，完成病历记录、治疗方案制定等工作 在科主任领导和上级医师指导下，负责科室一定范围的医疗、科研工作 按时查房，进行诊断、治疗及特殊诊疗操作，参加值班、门诊、会诊、出诊工作 | N58: 未建卡 | P58: https://campus.niuqizp.com/job-v8Y5aMNn5.html
A59: 58 | B59: 医疗健康 | C59: 理疗保健 | D59: 针灸推拿 | E59: BOSS分类 | F59: P1 | G59: 8 | H59: 8 | I59: =IF(H59<2,"证据少",IF(H59<5,"一般","较多")) | J59: 针灸推拿医师3、针灸推拿学1、针灸推拿1、针灸推拿科医师1、针灸推拿师1、针灸推拿科医生1 | K59: 本科5、硕士1、博士1、字段与正文不一致1 | L59: 中医学类6、医学技术类1、临床医学类1 | M59: 积极参与科室业务学习、病例讨论及技术提升培训，持续精进儿科中医推拿、针灸诊疗技术 配合科室完成日常运营、质控管理及领导交办的各项专项工作 维护理疗设备，记录治疗情况 | N59: jd_only_draft | O59: 从业者一手分享：未找到可入卡的已核正文，缺2名不同作者 日常体验、考核指标、发展路径与条件化风险：缺从业者证据，不用招聘宣传补齐 可核职责少于4条，不凑数 | P59: https://campus.niuqizp.com/job-v8l5nNaaL.html
A60: 59 | B60: 互联网/AI | C60: 运维/技术支持 | D60: 运维工程师 | E60: BOSS分类 | F60: P3 | G60: 8 | H60: 2 | I60: =IF(H60<2,"证据少",IF(H60<5,"一般","较多")) | J60: 南京区公司-网络运维工程师1、无锡市公司-动力能源运维工程师1、南京县公司（高淳/溧水）-网络运维工程师1、徐州县公司-网络运维工程师1、网络测量研发运维工程师11、泰州市公司-网络运维工程师1、徐州区公司-网络运维工程师1、南通市公司-网络运维工程师1 | K60: 硕士4、本科4 | L60: 不限专业7、计算机类1 | M60: 负责机房/数据中心电力及暖通系统等日常运维保障和管理工作 网络测量研发运维工程师1 参与网络空间测绘相关科研项目的研究开发、项目方案和技术文档的撰写整理等 | N60: jd_only_draft | O60: 从业者一手分享：未找到可入卡的已核正文，缺2名不同作者 日常体验、考核指标、发展路径与条件化风险：缺从业者证据，不用招聘宣传补齐 | P60: https://campus.niuqizp.com/job-v8l5CzzzL.html
A61: 60 | B61: 金融 | C61: 保险 | D61: 医学理赔/核保 | E61: 招聘样本补充 | F61: P1 | G61: 8 | H61: 6 | I61: =IF(H61<2,"证据少",IF(H61<5,"一般","较多")) | J61: 医学理赔5、医疗理赔岗2、人伤理赔作业岗1 | K61: 本科8 | L61: 临床医学类6、护理学类6、基础医学类4、公共卫生与预防医学类4、中医学类3、法学类3、口腔医学类2、动物医学类1、金融学类1、工商管理类1 | M61: 协助负责保险理赔工作 参与理赔制度体系建设、针对性提出理赔流程及系统优化建议 协助对理赔相关数据进行追踪及分析，形成风险提示及决策建议 | N61: jd_only_draft | O61: 从业者一手分享：未找到可入卡的已核正文，缺2名不同作者 日常体验、考核指标、发展路径与条件化风险：缺从业者证据，不用招聘宣传补齐 | P61: https://campus.niuqizp.com/job-v8m55Mt55.html
A62: 61 | B62: 互联网/AI | C62: 人工智能 | D62: 人工智能工程师（未细分） | E62: 招聘样本补充 | F62: P2 | G62: 8 | H62: 7 | I62: =IF(H62<2,"证据少",IF(H62<5,"一般","较多")) | J62: 人工智能工程师4、人工智能工程师（地点 武汉）1、建筑设计师,结构工程师,给排水工程师,暖通工程师,能源工程师,电气设计师,景观设计师,室内设计师,城乡规划师,总图设计师,工程管理人员,人工智能工程师,计算机工程师,安全工程师,消防工程师,机械工程师1、人工智能工程师-27届校招1、人工智能工程师-27届校招（北京、广州）1 | K62: 硕士4、本科3、博士1 | L62: 计算机类5、不限专业3、电子信息类1、电气类1、机械类1、建筑类1、管理科学与工程类1、设计学类1、金融学类1、经济学类1、统计学类1、数学类1 | M62: 参与算法研发和工程化部署，执行并完善标准化管理规范 完成上级领导安排的其他工作 建筑设计、结构工程、给水排水、暖通空调、 | N62: jd_only_draft | O62: 从业者一手分享：未找到可入卡的已核正文，缺2名不同作者 日常体验、考核指标、发展路径与条件化风险：缺从业者证据，不用招聘宣传补齐 | P62: https://campus.niuqizp.com/job-vky5C5ZC5.html
A63: 62 | B63: 医疗健康 | C63: 医生/医技 | D63: 超声科医生 | E63: BOSS分类 | G63: 7 | H63: 7 | I63: =IF(H63<2,"证据少",IF(H63<5,"一般","较多")) | J63: 超声科医师4、超声科医生2、超声科医师(J20513)1 | K63: 硕士3、博士1、本科1、字段与正文不一致1、未写1 | L63: 临床医学类3、不限专业2、基础医学类1、社会学类1 | M63: 负责全院门急诊、住院患者的超声诊断 - 准确书写超声诊断报告，确保影像资料完整、诊断依据充分 - 配合临床科室完成多学科会诊及特殊检查任务 | N63: 未建卡 | P63: https://campus.niuqizp.com/job-v8lNL55NN.html
A64: 63 | B64: 医疗健康 | C64: 医生/医技 | D64: 病理科医生 | E64: BOSS分类 | G64: 7 | H64: 7 | I64: =IF(H64<2,"证据少",IF(H64<5,"一般","较多")) | J64: 病理科医师5、病理科诊断医师（2027年校招）1、病理科学科带头人|骨干1 | K64: 硕士3、本科3、博士1 | L64: 临床医学类6 | M64: 完成病理科日常工作 负责常规病理标本的接收、登记、取材及制片工作，确保流程规范 在上级医师指导下进行显微镜下观察、诊断，出具初步病理报告 | N64: 未建卡 | P64: https://campus.niuqizp.com/job-v8m5CtatL.html
A65: 64 | B65: 医疗健康 | C65: 医疗销售 | D65: 医疗器械销售 | E65: BOSS分类 | F65: P1 | G65: 7 | H65: 7 | I65: =IF(H65<2,"证据少",IF(H65<5,"一般","较多")) | J65: 医疗器械销售代表3、医疗器械销售2、医疗器械销售（可实习）1、硬件工程师|医疗器械销售培训生1 | K65: 大专5、本科2 | L65: 不限专业2、社会学类1、生物医学工程类1、护理学类1、工商管理类1 | M65: 负责医疗器械产品的市场推广与客户开发，拓展医疗机构及渠道客户资源 收集市场反馈与竞争动态，协助制定有效的销售策略 完成销售任务目标，跟进销售流程各环节，确保业务顺利推进 | N65: jd_only_draft | O65: 从业者一手分享：未找到可入卡的已核正文，缺2名不同作者 日常体验、考核指标、发展路径与条件化风险：缺从业者证据，不用招聘宣传补齐 | P65: https://campus.niuqizp.com/job-vUl5nNCCa.html
A66: 65 | B66: 教育培训 | C66: 教师 | D66: 化学教师 | E66: BOSS分类 | F66: P2 | G66: 7 | H66: 5 | I66: =IF(H66<2,"证据少",IF(H66<5,"一般","较多")) | J66: 化学教师3、初|高中化学教师2、高中化学教师2 | K66: 本科6、硕士1 | L66: 材料类2、化学类1、教育学类1、植物生产类1 | M66: 教育/培训/院校 课后和家长进行沟通维护 完成上级交代的其他任务 | N66: jd_only_draft | O66: 从业者一手分享：未找到可入卡的已核正文，缺2名不同作者 日常体验、考核指标、发展路径与条件化风险：缺从业者证据，不用招聘宣传补齐 | P66: https://campus.niuqizp.com/job-v8r5MLtZZ.html
A67: 66 | B67: 物流/仓储/司机 | C67: 物流/运输 | D67: 物流专员 | E67: BOSS分类 | F67: P2 | G67: 7 | H67: 7 | I67: =IF(H67<2,"证据少",IF(H67<5,"一般","较多")) | J67: 物流管理3、物流管理岗2、2027校招-物流管理工程师(J11097)1、物流管理工程师（武汉）1 | K67: 本科6、硕士1 | L67: 物流管理与工程类3、不限专业2、工商管理类2、管理科学与工程类1、统计学类1 | M67: 负责对第三方存货仓库进行监管工作，不定时实地盘点，保障账账一致，账实相符 根据公司国际化发展需求，开展海外业务物流管理相关工作 负责跟进物流商务谈判、突发事件处理、物流风险隐患检查等其他物流相关工作 | N67: jd_only_draft | O67: 从业者一手分享：未找到可入卡的已核正文，缺2名不同作者 日常体验、考核指标、发展路径与条件化风险：缺从业者证据，不用招聘宣传补齐 | P67: https://campus.niuqizp.com/job-vYY5CLCLt.html
A68: 67 | B68: 咨询/翻译/法律 | C68: 咨询/调研 | D68: 知识产权/专利/商标代理人 | E68: BOSS分类 | F68: P3 | G68: 7 | H68: 6 | I68: =IF(H68<2,"证据少",IF(H68<5,"一般","较多")) | J68: 知识产权专员2、知识产权顾问1、知识产权工程师1、知识产权咨询研究（北方科技信息研究所）(J13602)1、专利|商标流程专员|知识产权顾问1、知识产权管培生1 | K68: 硕士4、本科1、字段与正文不一致1、未写1 | L68: 化学类2、不限专业1、药学类1、法学类1 | M68: 负责建立公司知识产权数据库，并及时更新，向研发人员汇报最新专利信息 负责为科研人员提供专利查询及公司各研发部门试验记录本归档工作 负责协助公司所有知识产权申报工作 | N68: jd_only_draft | O68: 从业者一手分享：未找到可入卡的已核正文，缺2名不同作者 日常体验、考核指标、发展路径与条件化风险：缺从业者证据，不用招聘宣传补齐 | P68: https://campus.niuqizp.com/job-vUY5NZn5a.html
A69: 68 | B69: 医疗健康 | C69: 其他医疗健康职位 | D69: 医疗机构运营管理 | E69: 招聘样本补充 | F69: P1 | G69: 7 | H69: 7 | I69: =IF(H69<2,"证据少",IF(H69<5,"一般","较多")) | J69: 运营管理岗3、运营管理管培生2、信息系统与运营管理助理研究员1、物流运营管理岗1 | K69: 硕士4、未写2、本科1 | L69: 管理科学与工程类2、临床医学类2、公共卫生与预防医学类2、财政学类1、不限专业1、经济学类1、工商管理类1、基础医学类1、药学类1 | M69: 按要求开展课程辅导课与实验课 为学生提供咨询与指导，并协调学生学术活动 以教学和行政辅助为主，完成既定工作后可开展科研相关事务 | N69: jd_only_draft | O69: 从业者一手分享：未找到可入卡的已核正文，缺2名不同作者 日常体验、考核指标、发展路径与条件化风险：缺从业者证据，不用招聘宣传补齐 | P69: https://campus.niuqizp.com/job-vk85nnazN.html
A70: 69 | B70: 医疗健康 | C70: 生物医药 | D70: 药理毒理研究员 | E70: BOSS分类 | F70: P1 | G70: 6 | H70: 4 | I70: =IF(H70<2,"证据少",IF(H70<5,"一般","较多")) | J70: 临床药理研究员（非实验岗）2、药理毒理研究员2、临床药理分析师1、临床药理助理研究员1 | K70: 硕士5、本科1 | L70: 临床医学类3、药学类3、数学类1 | M70: 参与临床试验方案及相关文件的撰写和审核 负责文献检索、数据收集和汇总分析 参与国际前沿创新药临床开发全流程 | N70: jd_only_draft | O70: 从业者一手分享：未找到可入卡的已核正文，缺2名不同作者 日常体验、考核指标、发展路径与条件化风险：缺从业者证据，不用招聘宣传补齐 | P70: https://campus.niuqizp.com/job-v8yNL55ZM.html
A71: 70 | B71: 医疗健康 | C71: 医疗器械 | D71: 医疗器械生产/质量管理 | E71: BOSS分类 | F71: P2 | G71: 6 | H71: 6 | I71: =IF(H71<2,"证据少",IF(H71<5,"一般","较多")) | J71: 医疗贸易|管培生质量管理1、质量管理类（27届校招）1、质量管理工程师(J13640)1、质量管理1、质量管理岗1、质量管理工程师1 | K71: 本科4、硕士2 | L71: 机械类3、药学类2、材料类2、工商管理类1、不限专业1、中药学类1、设计学类1、电气类1 | M71: 负责收集与医疗器械经营相关的法律、法规等有关规定，实施动态管理 组织医疗器械不良事件的收集与报告 协助开展质量管理培训并收集培训资料等 | N71: jd_only_draft | O71: 从业者一手分享：未找到可入卡的已核正文，缺2名不同作者 日常体验、考核指标、发展路径与条件化风险：缺从业者证据，不用招聘宣传补齐 可核职责少于4条，不凑数 | P71: https://campus.niuqizp.com/job-v8U5NzM5Z.html
A72: 71 | B72: 互联网/AI | C72: 运维/技术支持 | D72: 网络工程师 | E72: BOSS分类 | F72: P2 | G72: 6 | H72: 6 | I72: =IF(H72<2,"证据少",IF(H72<5,"一般","较多")) | J72: 网络工程师2、2026招聘网络工程师1、IT网络工程师1、通信网络工程师1、通信网络工程师-台州分公司1 | K72: 本科6 | L72: 不限专业3、计算机类3、管理科学与工程类1 | M72: 负责3/4/5G网络系统性能监控及优化，提升网络运营质量 负责移动网络用户语音/数据业务端到端分析优化工作 负责无线网络用户感知提升优化工作 | N72: jd_only_draft | O72: 从业者一手分享：未找到可入卡的已核正文，缺2名不同作者 日常体验、考核指标、发展路径与条件化风险：缺从业者证据，不用招聘宣传补齐 | P72: https://campus.niuqizp.com/job-vUy5nZMNZ.html
A73: 72 | B73: 互联网/AI | C73: 人工智能 | D73: 大模型算法 | E73: BOSS分类 | F73: P1 | G73: 6 | H73: 6 | I73: =IF(H73<2,"证据少",IF(H73<5,"一般","较多")) | J73: 大模型算法工程师1、VLM方向多模态大模型算法工程师1、2027招聘世界模型方向多模态大模型算法工程师1、2026招聘大模型算法工程师1、大模型算法研发1、【源点顶尖人才计划】大模型算法工程师(A130665)1 | K73: 硕士3、字段与正文不一致2、未写1 | L73: 计算机类3、不限专业1 | M73: 负责多模态大模型应用研发，训练行业多模态大模型、视频图像识别场景大模型 负责智能体应用软件开发，应用大模型、智能体技术开发智能查询、智能检索等智能体应用 负责研发特定场景下的目标检测、属性分类、场景分割等深度学习算法 | N73: jd_only_draft | O73: 从业者一手分享：未找到可入卡的已核正文，缺2名不同作者 日常体验、考核指标、发展路径与条件化风险：缺从业者证据，不用招聘宣传补齐 | P73: https://campus.niuqizp.com/job-v8U5MLntn.html
A74: 73 | B74: 电子/电气/通信 | C74: 通信 | D74: 通信技术工程师 | E74: BOSS分类 | F74: P2 | G74: 6 | H74: 6 | I74: =IF(H74<2,"证据少",IF(H74<5,"一般","较多")) | J74: 信息与通信工程2、通信设计（工作地点：总部及其分公司均可）（长春）1、通信工程师1、南宁分公司-通信工程项目管理1、通信网络技术运营-通信工程类（算力分公司）1 | K74: 本科4、博士2 | L74: 电子信息类2、不限专业2、计算机类1 | M74: 遥感信息处理2.多源数据融合3.卫星在轨处理 负责全市通信网络、云网、管线等工程项目的统筹立项、进度管控与全过程项目管理 统筹项目施工组织、资源协调、现场督导，把控工程建设质量、安全与施工规范 | N74: jd_only_draft | O74: 从业者一手分享：未找到可入卡的已核正文，缺2名不同作者 日常体验、考核指标、发展路径与条件化风险：缺从业者证据，不用招聘宣传补齐 | P74: https://campus.niuqizp.com/job-v8l5Ma5Ct.html
A75: 74 | B75: 销售 | C75: 销售 | D75: 销售工程师 | E75: BOSS分类 | F75: P2 | G75: 6 | H75: 5 | I75: =IF(H75<2,"证据少",IF(H75<5,"一般","较多")) | J75: 销售工程师4、医学应用研究|智能化开发|产品销售工程师|财务管培生|智能医生体验店经营岗集团管培生1、产品销售工程师1 | K75: 本科3、大专2、硕士1 | L75: 工商管理类3、基础医学类2、药学类1、不限专业1 | M75: 参与客户拜访、需求沟通、产品演示、技术交流和方案推荐 协助推进报价、招投标、合同签订、交付验收及回款工作 收集市场、客户及竞品信息，逐步成长为能够独立负责客户和销售任务的技术型业务人员 | N75: jd_only_draft | O75: 从业者一手分享：未找到可入卡的已核正文，缺2名不同作者 日常体验、考核指标、发展路径与条件化风险：缺从业者证据，不用招聘宣传补齐 | P75: https://campus.niuqizp.com/job-vk85CazMt.html
A76: 75 | B76: 销售 | C76: 销售行政/商务 | D76: 商务专员 | E76: BOSS分类 | F76: P2 | G76: 6 | H76: 6 | I76: =IF(H76<2,"证据少",IF(H76<5,"一般","较多")) | J76: 商务专员3、商务专员-海外-能源科技-深圳(J21765)1、电子商务专员1、电力电子商务专员1 | K76: 本科2、大专2、硕士1、未写1 | L76: 不限专业2、电子商务类2、材料类1、工商管理类1 | M76: 负责国际市场信息的收集、项目进度汇总并及时向上级汇报行情 客户开发与维护，有必要时与技术部门沟通 负责客户到访接待、安排 | N76: jd_only_draft | O76: 从业者一手分享：未找到可入卡的已核正文，缺2名不同作者 日常体验、考核指标、发展路径与条件化风险：缺从业者证据，不用招聘宣传补齐 | P76: https://campus.niuqizp.com/job-vls5MNnnL.html
... A79: 78 | B79: 咨询/翻译/法律 | C79: 翻译 | D79: 英语翻译 | E79: BOSS分类 | F79: P1 | G79: 6 | H79: 6 | I79: =IF(H79<2,"证据少",IF(H79<5,"一般","较多")) | J79: 英语翻译5、网站英语翻译实习生1 | K79: 本科4、未写2 | L79: 基础医学类2、外国语言文学类1、不限专业1 | M79: 处理外籍病人及家属往来邮件及口译工作 对医院其他人员进行翻译工作 负责公司外文来电、来函及各类文件的翻译工作，译稿内容准确并及时呈报领导 | N79: jd_only_draft | O79: 从业者一手分享：未找到可入卡的已核正文，缺2名不同作者 日常体验、考核指标、发展路径与条件化风险：缺从业者证据，不用招聘宣传补齐 | P79: https://campus.niuqizp.com/job-vUYNLZaNC.html
A80: 79 | B80: 医疗健康 | C80: 医生/医技 | D80: 医学检验 | E80: BOSS分类 | G80: 5 | H80: 4 | I80: =IF(H80<2,"证据少",IF(H80<5,"一般","较多")) | J80: 医学检验专业技术人员2、医学检验2、实习生-医学检验1 | K80: 大专4、本科1 | L80: 不限专业3、基础医学类1、计算机类1、医学技术类1 | M80: 根据医院安排负责医院日常门诊检验及检验科相关工作，服从医院其他工作安排 协助开展血液标本接收、信息核对、样本前处理等检验辅助工作 做好实验室仪器清洁维护、耗材整理、实验台账记录 | N80: 未建卡 | P80: https://campus.niuqizp.com/job-vkU5NnCMn.html
A81: 80 | B81: 医疗健康 | C81: 医疗器械 | D81: 试剂研发 | E81: BOSS分类 | F81: P1 | G81: 5 | H81: 4 | I81: =IF(H81<2,"证据少",IF(H81<5,"一般","较多")) | J81: 2026招聘试剂研发工程师1、化学发光试剂研发工程师1、分子诊断试剂研发工程师1、试剂研发工程师1、基因诊断试剂研发工程师1 | K81: 硕士3、本科2 | L81: 不限专业2、生物科学类1 | M81: 试剂研发工程师（本科、硕士） 负责分子诊断试剂产品的开发方案设计、实验执行与性能优化 负责产品的分析性能验证，完成实验设计、数据分析和相关报告撰写 | N81: jd_only_draft | O81: 从业者一手分享：未找到可入卡的已核正文，缺2名不同作者 日常体验、考核指标、发展路径与条件化风险：缺从业者证据，不用招聘宣传补齐 | P81: https://campus.niuqizp.com/job-vYY5taLaL.html
A82: 81 | B82: 互联网/AI | C82: 技术项目管理 | D82: 项目专员/助理 | E82: BOSS分类 | F82: P3 | G82: 5 | H82: 5 | I82: =IF(H82<2,"证据少",IF(H82<5,"一般","较多")) | J82: 项目助理实习生（项目测试）1、市场项目专员1、项目专员1、临床转化项目助理1、投资部项目助理1 | K82: 本科3、硕士2 | L82: 不限专业1、生物工程类1、临床医学类1、药学类1、金融学类1 | M82: 协助编写、执行和持续改进测试用例，整理测试结果与问题清单 负责市场部合约的管理，项目的启动，立项单的管理 负责定期了解知悉实验室的实验进程汇报给客户 | N82: jd_only_draft | O82: 从业者一手分享：未找到可入卡的已核正文，缺2名不同作者 日常体验、考核指标、发展路径与条件化风险：缺从业者证据，不用招聘宣传补齐 | P82: https://campus.niuqizp.com/job-v885nLnzM.html
A83: 82 | B83: 客服/运营 | C83: 电商运营 | D83: 国内电商运营 | E83: BOSS分类 | F83: P2 | G83: 5 | H83: 5 | I83: =IF(H83<2,"证据少",IF(H83<5,"一般","较多")) | J83: 电商专员3、电商运营岗1、电商运营1 | K83: 未写2、大专1、字段与正文不一致1、本科1 | L83: 电子商务类3、经济与贸易类3、不限专业1、计算机类1、电子信息类1、金融学类1、外国语言文学类1、物流管理与工程类1 | M83: 负责线上拼多多店铺运营，打单、发货 电商平台商品上架、信息维护 运营推广：制定运营方案，执行运营操作，打造精品，同时深挖产品线 | N83: jd_only_draft | O83: 从业者一手分享：未找到可入卡的已核正文，缺2名不同作者 日常体验、考核指标、发展路径与条件化风险：缺从业者证据，不用招聘宣传补齐 | P83: https://campus.niuqizp.com/job-v8l5ZaLLz.html
A84: 83 | B84: 医疗健康 | C84: 医生/医技 | D84: 医保/医院管理 | E84: 招聘样本补充 | F84: P1 | G84: 5 | H84: 5 | I84: =IF(H84<2,"证据少",IF(H84<5,"一般","较多")) | J84: 医务管理|数据审核|医保数据审核1、医院管理岗1、医保实习生1、临床护士|病案室编码员1、医保专员1 | K84: 本科4、硕士1 | L84: 药学类1、护理学类1、基础医学类1、临床医学类1、公共卫生与预防医学类1、法学类1、自动化类1、机械类1、建筑类1、管理科学与工程类1、工商管理类1、公共管理类1、材料类1 | M84: 协助医保政策咨询、参保患者答疑及窗口接待服务 参与医保结算单据的初审、整理及数据录入 协助医保系统操作、月度数据统计及报表制作 | N84: jd_only_draft | O84: 从业者一手分享：未找到可入卡的已核正文，缺2名不同作者 日常体验、考核指标、发展路径与条件化风险：缺从业者证据，不用招聘宣传补齐 | P84: https://campus.niuqizp.com/job-vYr5NaMNN.html
A85: 84 | B85: 医疗健康 | C85: 护士/护理 | D85: 导医 | E85: BOSS分类 | G85: 4 | H85: 4 | I85: =IF(H85<2,"证据少",IF(H85<5,"一般","较多")) | J85: 导医岗位1、导医1、超声科导医1、设备工程师|导医1 | K85: 本科2、大专2 | L85: 基础医学类2、计算机类1、不限专业1 | M85: 负责开诊前患者的接待和咨询 测量患者血压建立首诊档案 引导患者去相关科室就诊、取药、做检查 | N85: 未建卡 | P85: https://campus.niuqizp.com/job-vUs5N5LzZ.html
A86: 85 | B86: 医疗健康 | C86: 生物医药 | D86: 生物学研究人员 | E86: BOSS分类 | F86: P1 | G86: 4 | H86: 3 | I86: =IF(H86<2,"证据少",IF(H86<5,"一般","较多")) | J86: 分子生物学研究员3、生物研发资深科学家1 | K86: 硕士2、本科2 | L86: 生物科学类3、基础医学类1 | M86: 独立阅读文献，高效地完成试验设计或是操作 进行有效地分析实验数据和结果整理，积极与负责人沟通项目计划和进展 协助实验室日常管理 | N86: jd_only_draft | O86: 从业者一手分享：未找到可入卡的已核正文，缺2名不同作者 日常体验、考核指标、发展路径与条件化风险：缺从业者证据，不用招聘宣传补齐 | P86: https://campus.niuqizp.com/job-v88NLZMaz.html
A87: 86 | B87: 医疗健康 | C87: 临床试验 | D87: 临床医学经理/专员 | E87: BOSS分类 | F87: P1 | G87: 4 | H87: 3 | I87: =IF(H87<2,"证据少",IF(H87<5,"一般","较多")) | J87: 医学经理2、助理医学经理1、初级医学经理1 | K87: 硕士3、博士1 | L87: 不限专业3 | M87: 配合上级完成新产品的开发计划 与药政部门和临床专家沟通，完成相关试验设计 对于临床项目团队提供疾病和产品的相关知识培训 | N87: jd_only_draft | O87: 从业者一手分享：未找到可入卡的已核正文，缺2名不同作者 日常体验、考核指标、发展路径与条件化风险：缺从业者证据，不用招聘宣传补齐 | P87: https://campus.niuqizp.com/job-v8l5aznzN.html
A88: 87 | B88: 互联网/AI | C88: 数据 | D88: 数据采集 | E88: BOSS分类 | F88: P2 | G88: 4 | H88: 4 | I88: =IF(H88<2,"证据少",IF(H88<5,"一般","较多")) | J88: 数据采集师2、具身AI数据采集1、具身智能数据采集员|数据质检员|数据处理员1 | K88: 大专3、本科1 | L88: 不限专业2、计算机类2 | M88: 携带具身采集设备（头戴式摄像头）根据要求录制采集工作场景用于机器人的培训养成 主要负责信息的录入和采集等工作 具身智能数据采集员/数据质检员/数据处理员 | N88: jd_only_draft | O88: 从业者一手分享：未找到可入卡的已核正文，缺2名不同作者 日常体验、考核指标、发展路径与条件化风险：缺从业者证据，不用招聘宣传补齐 未抽出职责句，plain_language与daily_work留空 可核职责少于4条，不凑数 | P88: https://campus.niuqizp.com/job-vkUNL5tCM.html
A89: 88 | B89: 电子/电气/通信 | C89: 电子/硬件开发 | D89: 电子工程师 | E89: BOSS分类 | F89: P2 | G89: 4 | H89: 4 | I89: =IF(H89<2,"证据少",IF(H89<5,"一般","较多")) | J89: 电子工程师2、电子工程师(J10810)1、管培生,研发工程师,机械设计工程师,电子工程师,医疗器械维修工程师,海外市场销售专员,国内销售专员1 | K89: 字段与正文不一致1、硕士1、大专1、本科1 | L89: 不限专业2、计算机类2、临床医学类1、药学类1、生物工程类1、经济与贸易类1、外国语言文学类1、自动化类1、电气类1、机械类1、设计学类1 | M89: 培养方向为研发/技术/市场/国内销售/海外销售 研发工程师：工作城市为济南、杭州 机械设计工程师：工作城市为济南、杭州 | N89: jd_only_draft | O89: 从业者一手分享：未找到可入卡的已核正文，缺2名不同作者 日常体验、考核指标、发展路径与条件化风险：缺从业者证据，不用招聘宣传补齐 | P89: https://campus.niuqizp.com/job-vYU5aMNaZ.html
A90: 89 | B90: 销售 | C90: 教培销售 | D90: 课程顾问 | E90: BOSS分类 | F90: P3 | G90: 4 | H90: 2 | I90: =IF(H90<2,"证据少",IF(H90<5,"一般","较多")) | J90: 十堰课程顾问（本科）1、武汉课程顾问（本科）1、九江课程顾问（本科）1、课程顾问、市场营销1 | K90: 本科3、未写1 | L90: 金融学类3、经济学类3、财政学类3、法学类3、哲学类3、教育学类3、体育学类3、不限专业1 | M90: 根据组织下达的业绩目标，制定并执行年度/季度/月度工作计划，对结果负责 教育/培训/院校 记录客户的反馈与跟进记录 | N90: jd_only_draft | O90: 从业者一手分享：未找到可入卡的已核正文，缺2名不同作者 日常体验、考核指标、发展路径与条件化风险：缺从业者证据，不用招聘宣传补齐 可核职责少于4条，不凑数 | P90: https://campus.niuqizp.com/job-v8r5aZnzN.html
A91: 90 | B91: 人力/行政/法务 | C91: 法律服务 | D91: 法务专员/助理 | E91: BOSS分类 | F91: P2 | G91: 4 | H91: 4 | I91: =IF(H91<2,"证据少",IF(H91<5,"一般","较多")) | J91: 法务专员2、法务专员/助理1、[2027秋]法务专员(J16365)1 | K91: 本科4 | L91: 不限专业2、法学类1 | M91: 工作职责 1、处理法务工作 处理相关纠纷、诉讼 处理相关合同审核 | N91: jd_only_draft | O91: 从业者一手分享：未找到可入卡的已核正文，缺2名不同作者 日常体验、考核指标、发展路径与条件化风险：缺从业者证据，不用招聘宣传补齐 | P91: https://campus.niuqizp.com/job-vUy5CaZnL.html
A92: 91 | B92: 财务/审计/税务 | C92: 审计/税务 | D92: 审计 | E92: BOSS分类 | F92: P2 | G92: 4 | H92: 4 | I92: =IF(H92<2,"证据少",IF(H92<5,"一般","较多")) | J92: 审计岗3、【森大27届校招】西语审计储备1 | K92: 本科3、未写1 | L92: 金融学类2、经济学类2、财政学类2、统计学类2、工商管理类2、法学类1、计算机类1、管理科学与工程类1 | M92: 参与调研、分析、评估客户的业务流程和内部控制，向客户提供改善意见 协助主审人员完成后期整理工作，统计、整理附注披露数据及审计报告的出具 | N92: jd_only_draft | O92: 从业者一手分享：未找到可入卡的已核正文，缺2名不同作者 日常体验、考核指标、发展路径与条件化风险：缺从业者证据，不用招聘宣传补齐 未抽出职责句，plain_language与daily_work留空 可核职责少于4条，不凑数 | P92: https://campus.niuqizp.com/job-vYk5aNC5N.html
A93: 92 | B93: 餐饮 | C93: 前厅 | D93: 礼仪/迎宾/接待 | E93: BOSS分类 | F93: P2 | G93: 4 | H93: 4 | I93: =IF(H93<2,"证据少",IF(H93<5,"一般","较多")) | J93: 前台接待2、行政楼层接待1、客房接待1 | K93: 未写3、本科1 | L93: 旅游管理类4、工商管理类1 | M93: · 完成审记报告，为审记做准备 | N93: jd_only_draft | O93: 从业者一手分享：未找到可入卡的已核正文，缺2名不同作者 日常体验、考核指标、发展路径与条件化风险：缺从业者证据，不用招聘宣传补齐 未抽出职责句，plain_language与daily_work留空 可核职责少于4条，不凑数 | P93: https://campus.niuqizp.com/job-vmk5NaCz5.html
A94: 93 | B94: 教育培训 | C94: 教师 | D94: 物理教师 | E94: BOSS分类 | F94: P2 | G94: 4 | H94: 4 | I94: =IF(H94<2,"证据少",IF(H94<5,"一般","较多")) | J94: 物理教师2、初高中物理教师1、中学物理教师1 | K94: 本科3、硕士1 | L94: 物理学类4、教育学类1 | M94: 教育/培训/院校 | N94: jd_only_draft | O94: 从业者一手分享：未找到可入卡的已核正文，缺2名不同作者 日常体验、考核指标、发展路径与条件化风险：缺从业者证据，不用招聘宣传补齐 未抽出职责句，plain_language与daily_work留空 可核职责少于4条，不凑数 | P94: https://campus.niuqizp.com/job-vUs55nNaa.html
A95: 94 | B95: 教育培训 | C95: 运动健身 | D95: 体育/体能老师 | E95: BOSS分类 | F95: P2 | G95: 4 | H95: 4 | I95: =IF(H95<2,"证据少",IF(H95<5,"一般","较多")) | J95: 2027招聘体育老师1、小学体育老师1、体育老师（工作地海南澄迈）（济南）1、体育老师1 | K95: 本科3、大专1 | L95: 体育学类2、不限专业1 | M95: 设计和实施针对不同年龄段学员的体育课程，确保课程内容的趣味性和教育性 指导学员正确使用训练器材，确保训练过程安全无事故 依据教学大纲与课程标准，制定并实施适合学员的体适能训练课程 | N95: jd_only_draft | O95: 从业者一手分享：未找到可入卡的已核正文，缺2名不同作者 日常体验、考核指标、发展路径与条件化风险：缺从业者证据，不用招聘宣传补齐 | P95: https://campus.niuqizp.com/job-vYr5Mz5Z5.html
A96: 95 | B96: 房地产/建筑 | C96: 建筑/规划设计 | D96: 土木/土建/结构工程师 | E96: BOSS分类 | F96: P2 | G96: 4 | H96: 4 | I96: =IF(H96<2,"证据少",IF(H96<5,"一般","较多")) | J96: 通信网络技术运营-土木工程类（算力分公司）1、土木工程师1、土木工程1、结构工程师1 | K96: 硕士2、本科1、博士1 | L96: 土木类2、不限专业1、机械类1 | M96: 【岗位职责】从事土木类相关设计工作 飞行器设计与工程） | N96: jd_only_draft | O96: 从业者一手分享：未找到可入卡的已核正文，缺2名不同作者 日常体验、考核指标、发展路径与条件化风险：缺从业者证据，不用招聘宣传补齐 未抽出职责句，plain_language与daily_work留空 可核职责少于4条，不凑数 | P96: https://campus.niuqizp.com/job-v8lNLL5NZ.html
A97: 96 | B97: 客服/运营 | C97: 业务运营 | D97: 医学运营 | E97: 招聘样本补充 | F97: P1 | G97: 4 | H97: 3 | I97: =IF(H97<2,"证据少",IF(H97<5,"一般","较多")) | J97: 医学运营11、医疗运营管理类管培生1、医学运营31、医学运营专员1 | K97: 本科3、硕士1 | L97: 基础医学类3、临床医学类2、公共卫生与预防医学类1、药学类1 | M97: 支撑、指导智慧医疗系统的使用，包括培训、答疑等 与医学专家紧密协作，收集整理对于系统的反馈建议与意见 共同设计和执行模型医学评测策略，制定可量化的评测指标体系 | N97: jd_only_draft | O97: 从业者一手分享：未找到可入卡的已核正文，缺2名不同作者 日常体验、考核指标、发展路径与条件化风险：缺从业者证据，不用招聘宣传补齐 可核职责少于4条，不凑数 | P97: https://campus.niuqizp.com/job-vUY5ztLza.html
A98: 97 | B98: 医疗健康 | C98: 其他医疗健康职位 | D98: 公共卫生/疾控 | E98: 招聘样本补充 | F98: P1 | G98: 4 | H98: 4 | I98: =IF(H98<2,"证据少",IF(H98<5,"一般","较多")) | J98: 公共卫生专业人员1、公共卫生研究中级岗|公共卫生研究初级岗|公共卫生医师初级岗|公共卫生检验检测初级岗1、公共卫生医师-2027届高校毕业生1、公共卫生医师1 | K98: 未写2、硕士2 | L98: 公共卫生与预防医学类3、不限专业1 | M98: 负责辐射检测仪器、剂量测读系统维护、校准、期间核查 编制放射卫生检测报告，开展客户技术指导，识别辐射防护隐患，提出整改建议 | N98: jd_only_draft | O98: 从业者一手分享：未找到可入卡的已核正文，缺2名不同作者 日常体验、考核指标、发展路径与条件化风险：缺从业者证据，不用招聘宣传补齐 可核职责少于4条，不凑数 | P98: https://campus.niuqizp.com/job-vYk5antNn.html
A99: 98 | B99: 医疗健康 | C99: 医生/医技 | D99: 妇产科医生 | E99: BOSS分类 | G99: 3 | H99: 3 | I99: =IF(H99<2,"证据少",IF(H99<5,"一般","较多")) | J99: 妇产科医师1、妇产科医师岗1、妇产科规培医师1 | K99: 硕士3 | L99: 临床医学类2、社会学类1 | M99: 负责临床医师日常诊疗及科研工作 | N99: 未建卡 | P99: https://campus.niuqizp.com/job-v8m55nCNZ.html
A100: 99 | B100: 医疗健康 | C100: 生物医药 | D100: 药品生产 | E100: BOSS分类 | F100: P1 | G100: 3 | H100: 3 | I100: =IF(H100<2,"证据少",IF(H100<5,"一般","较多")) | J100: 原料生产工艺岗（药学类专业岗位）1、药品生产培训生1、药品生产管培生1 | K100: 本科1、硕士1、字段与正文不一致1 | L100: 药学类2、不限专业1、化工与制药类1 | M100: 负责审核批生产记录、数据采集、分析等 参与工艺优化、产能提升、技术改造等项目的日常推进与统筹管理 参与生产现场质量工艺巡检，及时发现并纠正工艺质量问题 | N100: jd_only_draft | O100: 从业者一手分享：未找到可入卡的已核正文，缺2名不同作者 日常体验、考核指标、发展路径与条件化风险：缺从业者证据，不用招聘宣传补齐 | P100: https://campus.niuqizp.com/job-v8rNLL5NN.html
A101: 100 | B101: 销售 | C101: 销售 | D101: 客户经理 | E101: BOSS分类 | F101: P2 | G101: 3 | H101: 3 | I101: =IF(H101<2,"证据少",IF(H101<5,"一般","较多")) | J101: 客户经理2、数字化营销客户经理（不限专业）1 | K101: 本科2、大专1 | L101: 金融学类2、经济学类1、财政学类1、数学类1、经济与贸易类1、工商管理类1、不限专业1 | N101: jd_only_draft | O101: 从业者一手分享：未找到可入卡的已核正文，缺2名不同作者 日常体验、考核指标、发展路径与条件化风险：缺从业者证据，不用招聘宣传补齐 未抽出职责句，plain_language与daily_work留空 可核职责少于4条，不凑数 | P101: https://campus.niuqizp.com/job-vYU5nzMCC.html
A102: 101 | B102: 零售/生活服务 | C102: 美容美发 | D102: 美容师 | E102: BOSS分类 | F102: P3 | G102: 3 | H102: 2 | I102: =IF(H102<2,"证据少",IF(H102<5,"一般","较多")) | J102: 美容师1、美容师头疗师1、头疗美容师1 | K102: 未写2、大专1 | L102: 不限专业2 | N102: jd_only_draft | O102: 从业者一手分享：未找到可入卡的已核正文，缺2名不同作者 日常体验、考核指标、发展路径与条件化风险：缺从业者证据，不用招聘宣传补齐 未抽出职责句，plain_language与daily_work留空 可核职责少于4条，不凑数 | P102: https://campus.niuqizp.com/job-vYy5zt5a5.html
...

Sheet 样本明细
A1: 样本ID | B1: 挂到的岗位节点 | C1: 匹配方式 | D1: 原始岗位名 | E1: 单位 | F1: 专业类 | G1: 专业来源 | H1: 学历 | I1: 学历字段冲突 | J1: 发布日期 | K1: 信息来源 | L1: 链接 | M1: 归类判断 | N1: 应归到
A2: vky5C5ZC5 | B2: 互联网/AI › 人工智能 › 人工智能工程师（未细分） | C2: 关键词 | D2: 人工智能工程师 | E2: 北京海博思创科技股份有限公司 | F2: 计算机类、电子信息类 | G2: 需求专业字段 | H2: 硕士 | J2: 2026-09-08 | K2: 内蒙古工业大学 | L2: https://campus.niuqizp.com/job-vky5C5ZC5.html
A3: vmm5MZ5MC | B3: 互联网/AI › 人工智能 › 人工智能工程师（未细分） | C3: 关键词 | D3: 人工智能工程师 | E3: 北京中电普华信息技术有限公司 | F3: 不限专业 | G3: 需求专业字段 | H3: 硕士 | J3: 2026-09-24 | K3: 南开大学 | L3: https://campus.niuqizp.com/job-vmm5MZ5MC.html
A4: vrm5ntZZL | B4: 互联网/AI › 人工智能 › 人工智能工程师（未细分） | C4: 关键词 | D4: 人工智能工程师 | E4: 中国大百科全书出版社有限公司 | F4: 计算机类 | G4: 需求专业字段 | H4: 硕士 | J4: 2026-09-16 | K4: 国聘 | L4: https://campus.niuqizp.com/job-vrm5ntZZL.html
A5: vwy5ZLz5M | B5: 互联网/AI › 人工智能 › 人工智能工程师（未细分） | C5: 关键词 | D5: 人工智能工程师 | E5: 华信永道（北京）科技股份有限公司 | F5: 金融学类、经济学类、计算机类、统计学类 | G5: 职责原文 | H5: 硕士 | J5: 2026-03-11 | K5: 河北工业大学 | L5: https://campus.niuqizp.com/job-vwy5ZLz5M.html
A6: vsy5azn5M | B6: 互联网/AI › 人工智能 › 人工智能工程师（未细分） | C6: 关键词 | D6: 人工智能工程师-27届校招 | E6: 卓望数码技术（深圳）有限公司 | F6: 不限专业 | G6: 需求专业字段 | H6: 本科 | J6: 2026-09-04 | K6: 国家大学生就业服务平台 | L6: https://campus.niuqizp.com/job-vsy5azn5M.html
A7: vyk5CNZLa | B7: 互联网/AI › 人工智能 › 人工智能工程师（未细分） | C7: 关键词 | D7: 人工智能工程师-27届校招（北京、广州） | E7: 卓望数码技术（深圳）有限公司 | F7: 计算机类、数学类 | G7: 需求专业字段 | H7: 本科 | J7: 2026-09-08 | K7: 华中农业大学 | L7: https://campus.niuqizp.com/job-vyk5CNZLa.html
A8: vky5Mttnn | B8: 互联网/AI › 人工智能 › 人工智能工程师（未细分） | C8: 关键词 | D8: 人工智能工程师（地点 武汉） | E8: 中国船舶集团有限公司第七一〇研究所 | F8: 不限专业 | G8: 需求专业字段 | H8: 博士 | J8: 2026-09-23 | K8: 前程无忧 | L8: https://campus.niuqizp.com/job-vky5Mttnn.html
A9: vlm5nZNNt | B9: 互联网/AI › 人工智能 › 人工智能工程师（未细分） | C9: 关键词 | D9: 建筑设计师,结构工程师,给排水工程师,暖通工程师,能源工程师,电气设计师,景观设计师,室内设计师,城乡规划师,总图设计师,工程管理人员,人工智能工程师,计算机工程师,安全工程师,消防工程师,机械工程师 | E9: 中国建筑设计研究院有限公司2027年应届毕业生 | F9: 计算机类、电气类、机械类、建筑类、管理科学与工程类、设计学类 | G9: 需求专业字段 | H9: 本科 | J9: 2026-09-15 | K9: 中国建筑设计研究院 | L9: https://campus.niuqizp.com/job-vlm5nZNNt.html
A10: vk85CZzzN | B10: 互联网/AI › 人工智能 › 医学AI/生物医学大模型 | C10: 关键词 | D10: 2027届-AIDD研究员 | E10: 上海泓博智源医药股份有限公司 | F10: 不限专业 | G10: 需求专业字段 | H10: 硕士 | J10: 2026-09-10 | K10: 南开大学 | L10: https://campus.niuqizp.com/job-vk85CZzzN.html
A11: vsl5Z5LZC | B11: 互联网/AI › 人工智能 › 医学AI/生物医学大模型 | C11: 关键词 | D11: AIDD研究员 | E11: 上海泓博智源医药股份有限公司 | F11: 药学类 | G11: 平台专业标签 | H11: 博士 | J11: 2026-03-13 | K11: 南开大学 | L11: https://campus.niuqizp.com/job-vsl5Z5LZC.html
A12: v8kNLZMaZ | B12: 互联网/AI › 人工智能 › 医学AI/生物医学大模型 | C12: 关键词 | D12: AIDD科学家 | E12: 杭州阿诺生物医药科技有限公司 | F12: 生物科学类 | G12: 需求专业字段 | H12: 字段与正文不一致 | I12: 是 | J12: 2026-10-04 | K12: 同济大学 | L12: https://campus.niuqizp.com/job-v8kNLZMaZ.html
A13: vYl5M55zN | B13: 互联网/AI › 人工智能 › 医学AI/生物医学大模型 | C13: 关键词 | D13: AI化学高级研究员 | E13: 青葵智造(北京)科技有限公司 | F13: 药学类 | G13: 职责原文 | H13: 博士 | J13: 2026-09-21 | K13: 浙江大学 | L13: https://campus.niuqizp.com/job-vYl5M55zN.html
A14: v8Y5na5NZ | B14: 互联网/AI › 人工智能 › 医学AI/生物医学大模型 | C14: 关键词 | D14: AI医疗反向工程师 | E14: 杭州疡医科技有限公司 | F14: 计算机类 | G14: 需求专业字段 | H14: 硕士 | J14: 2026-09-18 | K14: 中国计量大学 | L14: https://campus.niuqizp.com/job-v8Y5na5NZ.html
A15: vrm5aatLZ | B15: 互联网/AI › 人工智能 › 医学AI/生物医学大模型 | C15: 关键词 | D15: AI医疗大模型应用开发实习生 | E15: 南京普惠恒丰信息科技有限公司 | F15: 不限专业 | G15: 需求专业字段 | H15: 本科 | J15: 2026-09-05 | K15: 实习僧 | L15: https://campus.niuqizp.com/job-vrm5aatLZ.html
A16: vrk5ntMZa | B16: 互联网/AI › 人工智能 › 医学AI/生物医学大模型 | C16: 关键词 | D16: AI医疗行业—数据标注实习生 | E16: 上海宜云健康管理咨询有限公司 | F16: 不限专业 | G16: 需求专业字段 | H16: 未写 | J16: 2026-09-17 | K16: 实习僧 | L16: https://campus.niuqizp.com/job-vrk5ntMZa.html
A17: vYm55aMCZ | B17: 互联网/AI › 人工智能 › 医学AI/生物医学大模型 | C17: 关键词 | D17: 制药知识AI应用推广专员 | E17: 北京尚质合规科技有限公司 | F17: 基础医学类、药学类、化学类 | G17: 需求专业字段 | H17: 本科 | J17: 2025-10-10 | K17: 北京化工大学 | L17: https://campus.niuqizp.com/job-vYm55aMCZ.html
A18: vmk55aMCt | B18: 互联网/AI › 人工智能 › 医学AI/生物医学大模型 | C18: 关键词 | D18: 制药知识AI应用研究员 | E18: 北京尚质合规科技有限公司 | F18: 基础医学类、药学类、化学类、计算机类 | G18: 需求专业字段 | H18: 硕士 | J18: 2025-10-10 | K18: 北京化工大学 | L18: https://campus.niuqizp.com/job-vmk55aMCt.html
A19: vmU5t5zzZ | B19: 互联网/AI › 人工智能 › 医学AI/生物医学大模型 | C19: 关键词 | D19: 医学人工智能临床复合型医师|医学数据治理工程师|医学智能体工程师 | E19: 同济大学附属东方医院 | F19: 临床医学类、生物医学工程类 | G19: 职责原文 | H19: 硕士 | J19: 2026-01-09 | K19: 上海市东方医院 | L19: https://campus.niuqizp.com/job-vmU5t5zzZ.html
A20: manual-role_postings_2026-10-05_claude-22 | B20: 互联网/AI › 人工智能 › 医学AI/生物医学大模型 | C20: 关键词 | D20: 生物医学大模型研发 | E20: 未提供 | F20: 药学类、生物医学工程类、生物科学类、计算机类 | G20: 需求专业字段 | H20: 硕士 | K20: 用户提供 | L20: user-provided://2026-10-06/biomed-llm
A21: vmlNL5Zzn | B21: 互联网/AI › 人工智能 › 图像算法 | C21: BOSS末级名称 | D21: AI图像算法实习生 | E21: 西门子医疗系统有限公司 | F21: 不限专业 | G21: 需求专业字段 | H21: 本科 | J21: 2026-10-01 | K21: 实习僧 | L21: https://campus.niuqizp.com/job-vmlNL5Zzn.html
A22: vls5ztMMz | B22: 互联网/AI › 人工智能 › 大模型算法 | C22: BOSS末级名称 | D22: 2026招聘大模型算法工程师 | E22: 北京医者信息科技有限责任公司2026 | G22: 未写 | H22: 未写 | J22: 2026-06-04 | K22: 北京邮电大学世纪学院 | L22: https://campus.niuqizp.com/job-vls5ztMMz.html
A23: vlY5azazZ | B23: 互联网/AI › 人工智能 › 大模型算法 | C23: BOSS末级名称 | D23: 2027招聘世界模型方向多模态大模型算法工程师 | E23: 北京人形机器人创新中心有限公司2027 | F23: 计算机类 | G23: 职责原文 | H23: 硕士 | J23: 2026-09-03 | K23: 南京邮电大学 | L23: https://campus.niuqizp.com/job-vlY5azazZ.html
A24: vYl5azaaL | B24: 互联网/AI › 人工智能 › 大模型算法 | C24: BOSS末级名称 | D24: VLM方向多模态大模型算法工程师 | E24: 北京人形机器人创新中心有限公司 | G24: 未写 | H24: 字段与正文不一致 | I24: 是 | J24: 2026-09-03 | K24: 南京邮电大学 | L24: https://campus.niuqizp.com/job-vYl5azaaL.html
A25: vyk5CtnNL | B25: 互联网/AI › 人工智能 › 大模型算法 | C25: BOSS末级名称 | D25: 【源点顶尖人才计划】大模型算法工程师(A130665) | E25: 百川智能科技有限公司 | F25: 不限专业 | G25: 需求专业字段 | H25: 硕士 | J25: 2026-09-10 | K25: 实习僧 | L25: https://campus.niuqizp.com/job-vyk5CtnNL.html
A26: v8U5MLntn | B26: 互联网/AI › 人工智能 › 大模型算法 | C26: BOSS末级名称 | D26: 大模型算法工程师 | E26: 深圳乐动机器人股份有限公司B3 | F26: 计算机类 | G26: 需求专业字段 | H26: 字段与正文不一致 | I26: 是 | J26: 2026-09-22 | K26: 智联招聘 | L26: https://campus.niuqizp.com/job-v8U5MLntn.html
A27: vslNLzMC5 | B27: 互联网/AI › 人工智能 › 大模型算法 | C27: BOSS末级名称 | D27: 大模型算法研发 | E27: 公安部交通管理科学研究所 | F27: 计算机类 | G27: 需求专业字段 | H27: 硕士 | J27: 2026-10-05 | K27: 智联招聘 | L27: https://campus.niuqizp.com/job-vslNLzMC5.html
A28: vUm55MtZC | B28: 互联网/AI › 人工智能 › 数据标注/AI训练师 | C28: BOSS末级名称 | D28: AI数据标注 | E28: 北京愈心科技有限公司 | F28: 心理学类 | G28: 职责原文 | H28: 字段与正文不一致 | I28: 是 | J28: 2025-10-17 | K28: 南开大学 | L28: https://campus.niuqizp.com/job-vUm55MtZC.html
A29: vls5MMMML | B29: 互联网/AI › 人工智能 › 数据标注/AI训练师 | C29: BOSS末级名称 | D29: 数据标注 | E29: 保定新秀数字科技产业有限公司 | F29: 不限专业 | G29: 需求专业字段 | H29: 未写 | J29: 2026-09-30 | K29: 猎聘 | L29: https://campus.niuqizp.com/job-vls5MMMML.html
A30: vsY5aMCZt | B30: 互联网/AI › 人工智能 › 数据标注/AI训练师 | C30: BOSS末级名称 | D30: 数据标注员 | E30: 内蒙古古戈尔技术开发有限公司 | F30: 计算机类 | G30: 需求专业字段 | H30: 大专 | J30: 2026-09-07 | K30: 内蒙古机电职业技术学院 | L30: https://campus.niuqizp.com/job-vsY5aMCZt.html
A31: vsk5naLzz | B31: 互联网/AI › 人工智能 › 数据标注/AI训练师 | C31: BOSS末级名称 | D31: 数据标注员 | E31: 上饶市方迈网络科技有限公司 | F31: 计算机类 | G31: 需求专业字段 | H31: 字段与正文不一致 | I31: 是 | J31: 2026-09-18 | K31: 九江科技职业大学 | L31: https://campus.niuqizp.com/job-vsk5naLzz.html
A32: vyr5MNZNM | B32: 互联网/AI › 人工智能 › 数据标注/AI训练师 | C32: BOSS末级名称 | D32: 数据标注员 | E32: 贵州星长征教育科技有限公司 | F32: 不限专业 | G32: 需求专业字段 | H32: 未写 | J32: 2026-09-23 | K32: 猎聘 | L32: https://campus.niuqizp.com/job-vyr5MNZNM.html
A33: vYY5nCzM5 | B33: 互联网/AI › 人工智能 › 数据标注/AI训练师 | C33: BOSS末级名称 | D33: 数据标注师 | E33: 上饶市方迈网络科技有限公司 | F33: 计算机类 | G33: 需求专业字段 | H33: 大专 | J33: 2026-09-19 | K33: 南昌应用技术师范学院 | L33: https://campus.niuqizp.com/job-vYY5nCzM5.html
A34: vkr5Mt5Ln | B34: 互联网/AI › 人工智能 › 数据标注/AI训练师 | C34: BOSS末级名称 | D34: 数据标注师 | E34: 内蒙古启职点人才就业服务有限公司 | F34: 计算机类、电子信息类 | G34: 需求专业字段 | H34: 大专 | J34: 2026-09-23 | K34: 内蒙古财经大学 | L34: https://campus.niuqizp.com/job-vkr5Mt5Ln.html
A35: vym5MMttt | B35: 互联网/AI › 人工智能 › 数据标注/AI训练师 | C35: BOSS末级名称 | D35: 数据标注师 | E35: 上饶市方迈网络科技有限公司 | F35: 计算机类 | G35: 需求专业字段 | H35: 本科 | J35: 2026-09-29 | K35: 上饶职业技术学院 | L35: https://campus.niuqizp.com/job-vym5MMttt.html
A36: vrUNLLaLn | B36: 互联网/AI › 人工智能 › 数据标注/AI训练师 | C36: BOSS末级名称 | D36: 数据标注师AI训练师 | E36: 四梦数据（江西）有限公司 | F36: 法学类、计算机类 | G36: 需求专业字段 | H36: 本科 | J36: 2026-09-30 | K36: 江西省教育评估监测研究院 | L36: https://campus.niuqizp.com/job-vrUNLLaLn.html
A37: vll5anzLn | B37: 互联网/AI › 人工智能 › 数据标注/AI训练师 | C37: BOSS末级名称 | D37: 音乐标注项目-数据标注 | E37: 中洲联创（厦门）科技有限公司 | F37: 戏剧与影视学类、音乐与舞蹈学类 | G37: 需求专业字段 | H37: 本科 | J37: 2026-09-04 | K37: 国家大学生就业服务平台 | L37: https://campus.niuqizp.com/job-vll5anzLn.html
A38: vlkNLLatL | B38: 互联网/AI › 人工智能 › 算法工程师 | C38: BOSS末级名称 | D38: 人工智能算法工程师 | E38: 香港中文大学（深圳）城市地下空间及能源研究院 | F38: 计算机类、数学类 | G38: 需求专业字段 | H38: 硕士 | J38: 2026-09-30 | K38: 内蒙古自治区高校学生就业创业服务中心 | L38: https://campus.niuqizp.com/job-vlkNLLatL.html
A39: vYU5NLZaa | B39: 互联网/AI › 人工智能 › 算法工程师 | C39: BOSS末级名称 | D39: 医学研究型PM|医用人工智能算法工程师|转移转化与投资经理 | E39: 上海临床创新转化研究院有限公司 | F39: 基础医学类、临床医学类、中医学类、药学类、生物科学类、计算机类、自动化类、数学类、统计学类、物理学类 | G39: 需求专业字段 | H39: 硕士 | J39: 2025-10-22 | K39: 高校人才网 | L39: https://campus.niuqizp.com/job-vYU5NLZaa.html
A40: v8k5MZz5M | B40: 互联网/AI › 人工智能 › 算法工程师 | C40: BOSS末级名称 | D40: 图像与图谱算法工程师（地点 宜昌） | E40: 中国船舶集团有限公司第七一〇研究所 | F40: 不限专业 | G40: 需求专业字段 | H40: 硕士 | J40: 2026-09-24 | K40: 前程无忧 | L40: https://campus.niuqizp.com/job-v8k5MZz5M.html
A41: vlm5MtZMZ | B41: 互联网/AI › 人工智能 › 算法工程师 | C41: BOSS末级名称 | D41: 图像处理/视觉算法工程师 | E41: 中船星惯科技(武汉)有限公司 | F41: 计算机类 | G41: 需求专业字段 | H41: 硕士 | J41: 2026-09-23 | K41: 智联招聘 | L41: https://campus.niuqizp.com/job-vlm5MtZMZ.html
A42: vms5nzCNa | B42: 互联网/AI › 人工智能 › 算法工程师 | C42: BOSS末级名称 | D42: 图像处理AI方向算法工程师 | E42: 深圳市理邦精密仪器股份有限公司 | F42: 计算机类 | G42: 职责原文 | H42: 博士 | J42: 2026-09-17 | K42: 四川大学 | L42: https://campus.niuqizp.com/job-vms5nzCNa.html
A43: v8s5a55zC | B43: 互联网/AI › 人工智能 › 算法工程师 | C43: BOSS末级名称 | D43: 图像处理算法工程师超声,图像处理算法工程师内镜,信号处理算法工程师超声,光学工程师,AI算法工程师,材料开发工程师,临床工程师内镜 | E43: 开立医疗 | G43: 未写 | H43: 博士 | J43: 2026-08-22 | K43: 企业公众号开立招聘 | L43: https://campus.niuqizp.com/job-v8s5a55zC.html
A44: vYl5Mtt5t | B44: 互联网/AI › 人工智能 › 算法工程师 | C44: BOSS末级名称 | D44: 图像算法工程师 | E44: 武汉中导光电设备有限公司 | F44: 计算机类、数学类 | G44: 需求专业字段 | H44: 字段与正文不一致 | I44: 是 | J44: 2026-09-21 | K44: 国家大学生就业服务平台 | L44: https://campus.niuqizp.com/job-vYl5Mtt5t.html
A45: vkm5nC5MM | B45: 互联网/AI › 人工智能 › 算法工程师 | C45: BOSS末级名称 | D45: 图像算法工程师 | E45: 深圳市理邦精密仪器股份有限公司 | F45: 生物医学工程类 | G45: 职责原文 | H45: 硕士 | J45: 2026-09-17 | K45: 西安邮电大学 | L45: https://campus.niuqizp.com/job-vkm5nC5MM.html
A46: vwr5azLNZ | B46: 互联网/AI › 人工智能 › 算法工程师 | C46: BOSS末级名称 | D46: 图像算法工程师 | E46: 凌云光技术股份有限公司 | F46: 计算机类、电子信息类 | G46: 需求专业字段 | H46: 硕士 | J46: 2026-09-03 | K46: 国家大学生就业服务平台 | L46: https://campus.niuqizp.com/job-vwr5azLNZ.html
A47: vYy5CtLtC | B47: 互联网/AI › 人工智能 › 算法工程师 | C47: BOSS末级名称 | D47: 图像算法工程师（AI） | E47: 深圳明锐理想科技股份有限公司 | F47: 计算机类、自动化类 | G47: 职责原文 | H47: 硕士 | J47: 2026-09-09 | K47: 华中科技大学 | L47: https://campus.niuqizp.com/job-vYy5CtLtC.html
A48: vys5anMtn | B48: 互联网/AI › 人工智能 › 算法工程师 | C48: BOSS末级名称 | D48: 应用算法工程师 | E48: 江苏西励科技有限公司 | F48: 计算机类 | G48: 需求专业字段 | H48: 未写 | J48: 2026-09-06 | K48: 西安电子科技大学 | L48: https://campus.niuqizp.com/job-vys5anMtn.html
A49: vss5CLzLN | B49: 互联网/AI › 人工智能 › 算法工程师 | C49: BOSS末级名称 | D49: 控制算法工程师（博士） | E49: 深圳麦科田生物医疗技术股份有限公司 | F49: 不限专业 | G49: 需求专业字段 | H49: 博士 | J49: 2026-09-08 | K49: 天津理工大学 | L49: https://campus.niuqizp.com/job-vss5CLzLN.html
A50: vky55C5MN | B50: 互联网/AI › 人工智能 › 算法工程师 | C50: BOSS末级名称 | D50: 数学应用算法工程师 | E50: 北京数慧时空技术有限公司 | F50: 数学类 | G50: 需求专业字段 | H50: 硕士 | J50: 2025-10-10 | K50: 南开大学 | L50: https://campus.niuqizp.com/job-vky55C5MN.html
A51: vmm5NZZZZ | B51: 互联网/AI › 人工智能 › 算法工程师 | C51: BOSS末级名称 | D51: 深度学习图像算法工程师 | E51: 深圳深知未来智能有限公司 | F51: 计算机类 | G51: 需求专业字段 | H51: 本科 | J51: 2025-11-12 | K51: 长春医学高等专科学校 | L51: https://campus.niuqizp.com/job-vmm5NZZZZ.html
A52: vkU5z5tLN | B52: 互联网/AI › 人工智能 › 算法工程师 | C52: BOSS末级名称 | D52: 研发工程师,实施工程师,算法工程师,数据工程师,产品经理,项目经理,业务顾问,客户经理,销售咨询生 | E52: 卫宁健康科技集团股份有限公司 | G52: 未写 | H52: 本科 | J52: 2026-05-14 | K52: 卫宁招聘 | L52: https://campus.niuqizp.com/job-vkU5z5tLN.html
A53: v8U5nLMZL | B53: 互联网/AI › 人工智能 › 算法工程师 | C53: BOSS末级名称 | D53: 算法工程师 | E53: 纳米维景(上海)医疗科技有限公司 | F53: 不限专业 | G53: 需求专业字段 | H53: 本科 | J53: 2026-09-15 | K53: 实习僧 | L53: https://campus.niuqizp.com/job-v8U5nLMZL.html
A54: v8m5tMNaC | B54: 互联网/AI › 人工智能 › 算法工程师 | C54: BOSS末级名称 | D54: 算法工程师 | E54: 深圳麦科田生物医疗技术股份有限公司 | F54: 基础医学类 | G54: 平台专业标签 | H54: 硕士 | J54: 2026-03-09 | K54: 天津医科大学 | L54: https://campus.niuqizp.com/job-v8m5tMNaC.html
A55: vr85MLCLM | B55: 互联网/AI › 人工智能 › 算法工程师 | C55: BOSS末级名称 | D55: 算法工程师 | E55: 深圳华大智造科技股份有限公司 | F55: 不限专业 | G55: 需求专业字段 | H55: 硕士 | J55: 2026-09-22 | K55: 南京航空航天大学 | L55: https://campus.niuqizp.com/job-vr85MLCLM.html
A56: vry5n5tnz | B56: 互联网/AI › 人工智能 › 算法工程师 | C56: BOSS末级名称 | D56: 算法工程师 | E56: 北京谊安医疗系统股份有限公司 | F56: 生物医学工程类 | G56: 职责原文 | H56: 硕士 | J56: 2026-09-14 | K56: 河北工业大学 | L56: https://campus.niuqizp.com/job-vry5n5tnz.html
A57: vwY5nnntN | B57: 互联网/AI › 人工智能 › 算法工程师 | C57: BOSS末级名称 | D57: 算法工程师 | E57: 深圳华大智造科技有限公司 | F57: 计算机类 | G57: 需求专业字段 | H57: 硕士 | J57: 2026-09-20 | K57: 华东理工大学 | L57: https://campus.niuqizp.com/job-vwY5nnntN.html
A58: vyU5tnLzC | B58: 互联网/AI › 人工智能 › 算法工程师 | C58: BOSS末级名称 | D58: 算法工程师 | E58: 深圳麦科田生物医疗技术股份有限公司 | F58: 基础医学类 | G58: 平台专业标签 | H58: 硕士 | J58: 2026-03-05 | K58: 西安邮电大学 | L58: https://campus.niuqizp.com/job-vyU5tnLzC.html
A59: vsk5MLnZZ | B59: 互联网/AI › 人工智能 › 算法工程师 | C59: BOSS末级名称 | D59: 系统算法工程师 | E59: 深圳鲲为科技有限公司D1 | F59: 计算机类 | G59: 需求专业字段 | H59: 硕士 | J59: 2026-09-22 | K59: 智联招聘 | L59: https://campus.niuqizp.com/job-vsk5MLnZZ.html
A60: vw85MMnnL | B60: 互联网/AI › 人工智能 › 算法工程师 | C60: BOSS末级名称 | D60: 视觉算法工程师 | E60: 马栏山音视频实验室 | F60: 计算机类、数学类 | G60: 需求专业字段 | H60: 硕士 | J60: 2026-09-29 | K60: 中山大学 | L60: https://campus.niuqizp.com/job-vw85MMnnL.html
A61: v8r5MMZ5z | B61: 互联网/AI › 人工智能 › 算法研究员 | C61: BOSS末级名称 | D61: AI物质科学算法研究员-药物 | E61: 上海市青浦复旦未来技术研究院 | F61: 不限专业 | G61: 需求专业字段 | H61: 字段与正文不一致 | I61: 是 | J61: 2026-09-29 | K61: 华东理工大学 | L61: https://campus.niuqizp.com/job-v8r5MMZ5z.html
A62: vwU5MMZZ5 | B62: 互联网/AI › 人工智能 › 算法研究员 | C62: BOSS末级名称 | D62: AI物质表征算法研究员 | E62: 上海市青浦复旦未来技术研究院 | F62: 不限专业 | G62: 需求专业字段 | H62: 硕士 | J62: 2026-09-29 | K62: 华东理工大学 | L62: https://campus.niuqizp.com/job-vwU5MMZZ5.html
A63: vs85ZzLNN | B63: 互联网/AI › 后端开发 › C/C++ | C63: BOSS末级名称 | D63: 医学影像工程师实习生|C++医学影像工程师 | E63: 贝麦克斯科技 | F63: 生物医学工程类 | G63: 需求专业字段 | H63: 本科 | J63: 2026-03-27 | K63: 广州新华学院 | L63: https://campus.niuqizp.com/job-vs85ZzLNN.html
A64: vlY5CaMNa | B64: 互联网/AI › 后端开发 › 软件开发工程师（未细分） | C64: 关键词 | D64: ai软件工程师 | E64: 上海玖熠半导体科技有限公司 | F64: 计算机类 | G64: 需求专业字段 | H64: 硕士 | J64: 2026-09-11 | K64: 智联招聘 | L64: https://campus.niuqizp.com/job-vlY5CaMNa.html
A65: vmm5tNnnn | B65: 互联网/AI › 后端开发 › 软件开发工程师（未细分） | C65: 关键词 | D65: 信号处理应用软件开发工程师 | E65: 清华大学精密仪器系 | F65: 自动化类 | G65: 职责原文 | H65: 本科 | J65: 2026-01-22 | K65: 高校人才网 | L65: https://campus.niuqizp.com/job-vmm5tNnnn.html
A66: vlr5zzCNM | B66: 互联网/AI › 后端开发 › 软件开发工程师（未细分） | C66: 关键词 | D66: 图像处理算法工程师,信号处理算法工程师,AI算法工程师,应用软件工程师,光机结构工程师,电源工程师,嵌入式硬件工程师,产品验证工程师,机械工程师,全球技术支持工程师 | E66: 开立医疗 | F66: 生物医学工程类、计算机类、自动化类、机械类、材料类、数学类 | G66: 需求专业字段 | H66: 硕士 | J66: 2026-06-24 | K66: 企业公众号开立招聘 | L66: https://campus.niuqizp.com/job-vlr5zzCNM.html
A67: vyy5z5LCa | B67: 互联网/AI › 后端开发 › 软件开发工程师（未细分） | C67: 关键词 | D67: 嵌入式软件工程师 | E67: 深圳市安保医疗科技股份有限公司 | F67: 计算机类、自动化类 | G67: 职责原文 | H67: 本科 | J67: 2026-05-11 | K67: 西安工程大学 | L67: https://campus.niuqizp.com/job-vyy5z5LCa.html
A68: vy85ntCt5 | B68: 互联网/AI › 后端开发 › 软件开发工程师（未细分） | C68: 关键词 | D68: 应用/软件工程师（汽车） | E68: 小华半导体有限公司 | F68: 计算机类、电子信息类、机械类、材料类 | G68: 需求专业字段 | H68: 硕士 | J68: 2026-09-16 | K68: 智联招聘 | L68: https://campus.niuqizp.com/job-vy85ntCt5.html
A69: vUU5CttzM | B69: 互联网/AI › 后端开发 › 软件开发工程师（未细分） | C69: 关键词 | D69: 应用软件工程师 | E69: 合众思壮校招 | F69: 不限专业 | G69: 需求专业字段 | H69: 本科 | J69: 2026-09-09 | K69: 前程无忧 | L69: https://campus.niuqizp.com/job-vUU5CttzM.html
A70: vly5MttaL | B70: 互联网/AI › 后端开发 › 软件开发工程师（未细分） | C70: 关键词 | D70: 应用软件工程师（地点 武汉） | E70: 中国船舶集团有限公司第七一〇研究所 | F70: 不限专业 | G70: 需求专业字段 | H70: 硕士 | J70: 2026-09-23 | K70: 前程无忧 | L70: https://campus.niuqizp.com/job-vly5MttaL.html
A71: vwl55CnZz | B71: 互联网/AI › 后端开发 › 软件开发工程师（未细分） | C71: 关键词 | D71: 生物实验工程师|上位机软件工程师 | E71: 广州市宝创生物技术有限公司 | F71: 生物医学工程类 | G71: 需求专业字段 | H71: 本科 | J71: 2025-10-13 | K71: 广州新华学院 | L71: https://campus.niuqizp.com/job-vwl55CnZz.html
A72: v8m5ntZZn | B72: 互联网/AI › 后端开发 › 软件开发工程师（未细分） | C72: 关键词 | D72: 软件工程师 | E72: 中国大百科全书出版社有限公司 | F72: 计算机类 | G72: 需求专业字段 | H72: 硕士 | J72: 2026-09-16 | K72: 国聘 | L72: https://campus.niuqizp.com/job-v8m5ntZZn.html
A73: v8s5CZZtL | B73: 互联网/AI › 后端开发 › 软件开发工程师（未细分） | C73: 关键词 | D73: 软件工程师 | E73: 上海远宽能源科技有限公司 | F73: 不限专业 | G73: 需求专业字段 | H73: 本科 | J73: 2026-09-09 | K73: 北极星 | L73: https://campus.niuqizp.com/job-v8s5CZZtL.html
... A77: vmY5CntCa | B77: 互联网/AI › 后端开发 › 软件开发工程师（未细分） | C77: 关键词 | D77: 软件工程师 | E77: 中车株洲电力机车研究所有限公司 | F77: 电气类 | G77: 需求专业字段 | H77: 本科 | J77: 2026-09-12 | K77: 智联招聘 | L77: https://campus.niuqizp.com/job-vmY5CntCa.html
A78: vml5M5Lnn | B78: 互联网/AI › 后端开发 › 软件开发工程师（未细分） | C78: 关键词 | D78: 软件工程师 | E78: 上海交通大学浦江国际学院任中强课题组 | G78: 未写 | H78: 未写 | J78: 2026-09-20 | K78: 上海交通大学人才招聘网 | L78: https://campus.niuqizp.com/job-vml5M5Lnn.html
A79: vrlNL5CZ5 | B79: 互联网/AI › 后端开发 › 软件开发工程师（未细分） | C79: 关键词 | D79: 软件工程师 | E79: 上海惟甲科技有限公司 | F79: 计算机类 | G79: 职责原文 | H79: 硕士 | J79: 2026-09-30 | K79: 浙江大学 | L79: https://campus.niuqizp.com/job-vrlNL5CZ5.html
A80: vsY5Mtnna | B80: 互联网/AI › 后端开发 › 软件开发工程师（未细分） | C80: 关键词 | D80: 软件工程师 | E80: 北京计算机技术及应用研究所 | F80: 计算机类 | G80: 职责原文 | H80: 硕士 | J80: 2026-09-23 | K80: 浙江大学 | L80: https://campus.niuqizp.com/job-vsY5Mtnna.html
A81: vwY5t555z | B81: 互联网/AI › 后端开发 › 软件开发工程师（未细分） | C81: 关键词 | D81: 软件工程师 | E81: 上海交通大学材料科学与工程学院凝固科学与技术研究所 | F81: 计算机类 | G81: 职责原文 | H81: 未写 | J81: 2026-01-06 | K81: 上海交通大学人才招聘网 | L81: https://campus.niuqizp.com/job-vwY5t555z.html
A82: vmY5MttZt | B82: 互联网/AI › 后端开发 › 软件开发工程师（未细分） | C82: 关键词 | D82: 软件工程师（地点 武汉） | E82: 中国船舶集团有限公司第七一〇研究所 | F82: 不限专业 | G82: 需求专业字段 | H82: 硕士 | J82: 2026-09-23 | K82: 前程无忧 | L82: https://campus.niuqizp.com/job-vmY5MttZt.html
A83: v8U5aZ5CN | B83: 互联网/AI › 后端开发 › 软件开发工程师（未细分） | C83: 关键词 | D83: 软件开发 | E83: 南京电子工程研究所（中国电子科技集团公司第二十八研究所） | F83: 计算机类 | G83: 需求专业字段 | H83: 硕士 | J83: 2026-09-02 | K83: 国家大学生就业服务平台 | L83: https://campus.niuqizp.com/job-v8U5aZ5CN.html
A84: vlm5atLzt | B84: 互联网/AI › 后端开发 › 软件开发工程师（未细分） | C84: 关键词 | D84: 软件开发工程师 | E84: 特变电工股份有限公司新疆变压器厂 | F84: 计算机类、机械类 | G84: 需求专业字段 | H84: 本科 | J84: 2026-08-31 | K84: 国家大学生就业服务平台 | L84: https://campus.niuqizp.com/job-vlm5atLzt.html
A85: vsYNLLtNM | B85: 互联网/AI › 后端开发 › 软件开发工程师（未细分） | C85: 关键词 | D85: 软件开发工程师 | E85: 中国科学院数学与系统科学研究院 | F85: 计算机类 | G85: 职责原文 | H85: 本科 | J85: 2026-09-29 | K85: 高校人才网 | L85: https://campus.niuqizp.com/job-vsYNLLtNM.html
A86: vyl5C5zzN | B86: 互联网/AI › 后端开发 › 软件开发工程师（未细分） | C86: 关键词 | D86: 软件开发工程师 | E86: 上海复矽源半导体科技有限公司 | F86: 机械类、材料类、数学类、统计学类、物理学类 | G86: 需求专业字段 | H86: 硕士 | J86: 2026-09-08 | K86: 杭州电子科技大学 | L86: https://campus.niuqizp.com/job-vyl5C5zzN.html
A87: vmy5NNzCL | B87: 互联网/AI › 后端开发 › 软件开发工程师（未细分） | C87: 关键词 | D87: 软件开发工程师,数据分析师,产品经理,UI,UX设计师,算法工程师,运维工程师,医学内容编辑,客户成功经理,市场推广专员,人力资源专员 | E87: 明天医网 | G87: 未写 | H87: 本科 | J87: 2025-11-03 | K87: 企业公众号明天医网 | L87: https://campus.niuqizp.com/job-vmy5NNzCL.html
A88: vrU5CCZCC | B88: 互联网/AI › 后端开发 › 软件开发工程师（未细分） | C88: 关键词 | D88: 高级高压系统工程师,高级车载能源工程师,高级底盘工程师,高级产品设计工程师,高级CAE工程师,高级车身集成工程师,高级造型设计师,高级整车集成工程师,高级车型成本分析工程师,高级前瞻模具工程师,编程工程师,高级软件工程师 | E88: 比亚迪汽车工程研究院比亚迪2027届全球校园 | F88: 法学类、计算机类、自动化类、电气类、机械类、材料类、管理科学与工程类、交通运输类、物流管理与工程类、统计学类、物理学类、工商管理类、设计学类、美术学类 | G88: 需求专业字段 | H88: 未写 | J88: 2026-09-11 | K88: 微信公众号比亚迪招聘 | L88: https://campus.niuqizp.com/job-vrU5CCZCC.html
A89: vrr5zMNNn | B89: 互联网/AI › 技术项目管理 › 项目专员/助理 | C89: BOSS末级名称 | D89: 临床转化项目助理 | E89: 北京大学第三医院药物临床试验机构 | F89: 药学类 | G89: 平台专业标签 | H89: 硕士 | J89: 2026-08-04 | K89: 北京大学第三医院 | L89: https://campus.niuqizp.com/job-vrr5zMNNn.html
A90: vkU5ZLLCL | B90: 互联网/AI › 技术项目管理 › 项目专员/助理 | C90: BOSS末级名称 | D90: 市场项目专员 | E90: 上海英拜生物科技有限公司 | F90: 生物工程类 | G90: 职责原文 | H90: 本科 | J90: 2026-03-10 | K90: 中国科学技术大学 | L90: https://campus.niuqizp.com/job-vkU5ZLLCL.html
A91: vsl5zz5LC | B91: 互联网/AI › 技术项目管理 › 项目专员/助理 | C91: BOSS末级名称 | D91: 投资部项目助理 | E91: 中经城投建设集团空轨设计研究有限公司 | F91: 金融学类 | G91: 职责原文 | H91: 硕士 | J91: 2026-06-15 | K91: 南开大学 | L91: https://campus.niuqizp.com/job-vsl5zz5LC.html
A92: vlU5zZMNM | B92: 互联网/AI › 技术项目管理 › 项目专员/助理 | C92: BOSS末级名称 | D92: 项目专员 | E92: 首都医科大学附属北京胸科医院中国CDC结核病防治临床中心(疾病预防控制处) | F92: 临床医学类 | G92: 职责原文 | H92: 本科 | J92: 2026-06-12 | K92: 首都医科大学附属北京胸科医院 | L92: https://campus.niuqizp.com/job-vlU5zZMNM.html
A93: v885nLnzM | B93: 互联网/AI › 技术项目管理 › 项目专员/助理 | C93: BOSS末级名称 | D93: 项目助理实习生（项目测试） | E93: 华超神控(上海)科技有限公司 | F93: 不限专业 | G93: 需求专业字段 | H93: 本科 | J93: 2026-09-15 | K93: 实习僧 | L93: https://campus.niuqizp.com/job-v885nLnzM.html
A94: vYU5CLtZt | B94: 互联网/AI › 技术项目管理 › 项目经理/主管 | C94: BOSS末级名称 | D94: 东莞分公司-项目经理 | E94: 中国移动通信集团广东有限公司 | F94: 不限专业 | G94: 需求专业字段 | H94: 本科 | J94: 2026-09-07 | K94: 国聘 | L94: https://campus.niuqizp.com/job-vYU5CLtZt.html
A95: vYr5NLz5M | B95: 互联网/AI › 技术项目管理 › 项目经理/主管 | C95: BOSS末级名称 | D95: 公共绩效与信息化研究中心项目主管 | E95: 复旦大学发展研究院 | F95: 经济学类、统计学类 | G95: 需求专业字段 | H95: 硕士 | J95: 2025-10-22 | K95: 复旦大学人事处 | L95: https://campus.niuqizp.com/job-vYr5NLz5M.html
A96: vrY5n5ttN | B96: 互联网/AI › 技术项目管理 › 项目经理/主管 | C96: BOSS末级名称 | D96: 医药客户项目经理 | E96: 上海数图健康医药科技有限公司 | F96: 临床医学类、工商管理类 | G96: 职责原文 | H96: 本科 | J96: 2026-09-14 | K96: 中国药科大学 | L96: https://campus.niuqizp.com/job-vrY5n5ttN.html
A97: vmU5MMtZa | B97: 互联网/AI › 技术项目管理 › 项目经理/主管 | C97: BOSS末级名称 | D97: 生产项目经理 | E97: 普洛药业股份有限公司 | F97: 药学类 | G97: 需求专业字段 | H97: 硕士 | J97: 2026-09-29 | K97: 浙江中医药大学 | L97: https://campus.niuqizp.com/job-vmU5MMtZa.html
A98: vsY5nCZ5n | B98: 互联网/AI › 技术项目管理 › 项目经理/主管 | C98: BOSS末级名称 | D98: 生产项目经理 | E98: 普洛药业股份有限公司 | F98: 基础医学类 | G98: 平台专业标签 | H98: 未写 | J98: 2026-09-18 | K98: 浙江大学 | L98: https://campus.niuqizp.com/job-vsY5nCZ5n.html
A99: vUm5MMCLz | B99: 互联网/AI › 技术项目管理 › 项目经理/主管 | C99: BOSS末级名称 | D99: 石嘴山分公司-项目经理 | E99: 中国移动通信集团宁夏有限公司 | F99: 不限专业 | G99: 需求专业字段 | H99: 本科 | J99: 2026-09-29 | K99: 国聘 | L99: https://campus.niuqizp.com/job-vUm5MMCLz.html
... A102: vlr5CNaMC | B102: 互联网/AI › 技术项目管理 › 项目经理/主管 | C102: BOSS末级名称 | D102: 项目主管岗位 | E102: 复旦大学全球健康治理高等研究院 | F102: 临床医学类、公共卫生与预防医学类 | G102: 职责原文 | H102: 硕士 | J102: 2026-09-08 | K102: 复旦大学人事处 | L102: https://campus.niuqizp.com/job-vlr5CNaMC.html
A103: vU85Caa5t | B103: 互联网/AI › 技术项目管理 › 项目经理/主管 | C103: BOSS末级名称 | D103: 项目经理 | E103: 湖南华纳大药厂股份有限公司 | G103: 未写 | H103: 博士 | J103: 2026-09-11 | K103: 四川省教育厅就业指导中心 | L103: https://campus.niuqizp.com/job-vU85Caa5t.html
A104: vr85MMNtt | B104: 互联网/AI › 技术项目管理 › 项目经理/主管 | C104: BOSS末级名称 | D104: 项目经理(英语/日语/韩语) | E104: 通力科技股份有限公司 | G104: 未写 | H104: 本科 | J104: 2026-09-29 | K104: 中国地质大学(武汉) | L104: https://campus.niuqizp.com/job-vr85MMNtt.html
A105: vkm5CLNC5 | B105: 互联网/AI › 技术项目管理 › 项目经理/主管 | C105: BOSS末级名称 | D105: 项目经理（2027届校招） | E105: 湖南华纳大药厂股份有限公司 | F105: 不限专业 | G105: 需求专业字段 | H105: 博士 | J105: 2026-09-07 | K105: 北森 | L105: https://campus.niuqizp.com/job-vkm5CLNC5.html
...

Sheet 专业连线
A1: 专业类 | B1: 行业 | C1: 岗位 | D1: 样本数 | E1: 单位数 | F1: 证据强度 | G1: 仅平台标签样本 | H1: 学历分布 | I1: 示例链接 | J1: 连线判断 | K1: 问题说明
A2: 不限专业 | B2: 医疗健康 | C2: 临床医生（科室未细分） | D2: 15 | E2: 13 | F2: =IF(E2<2,"证据少",IF(E2<5,"一般","较多")) | G2: 0 | H2: 硕士6、本科5、未写3、博士1 | I2: https://campus.niuqizp.com/job-v8kNLzzM5.html
A3: 不限专业 | B3: 医疗健康 | C3: 医疗产品技术支持 | D3: 11 | E3: 11 | F3: =IF(E3<2,"证据少",IF(E3<5,"一般","较多")) | G3: 0 | H3: 本科6、硕士4、未写1 | I3: https://campus.niuqizp.com/job-v8s5nNntZ.html
A4: 不限专业 | B4: 人力/行政/法务 | C4: 人力资源专员/助理 | D4: 10 | E4: 9 | F4: =IF(E4<2,"证据少",IF(E4<5,"一般","较多")) | G4: 0 | H4: 本科8、字段与正文不一致1、硕士1 | I4: https://campus.niuqizp.com/job-v8YNLNZCL.html
A5: 不限专业 | B5: 市场/公关/广告 | C5: 市场营销策划 | D5: 9 | E5: 9 | F5: =IF(E5<2,"证据少",IF(E5<5,"一般","较多")) | G5: 0 | H5: 未写4、本科4、字段与正文不一致1 | I5: https://campus.niuqizp.com/job-v8Y5ztLNL.html
A6: 不限专业 | B6: 医疗健康 | C6: 医药代表 | D6: 12 | E6: 7 | F6: =IF(E6<2,"证据少",IF(E6<5,"一般","较多")) | G6: 0 | H6: 本科11、大专1 | I6: https://campus.niuqizp.com/job-v8U5MMtNN.html
A7: 不限专业 | B7: 生产制造 | C7: 机械工程师 | D7: 7 | E7: 7 | F7: =IF(E7<2,"证据少",IF(E7<5,"一般","较多")) | G7: 0 | H7: 本科4、硕士2、大专1 | I7: https://campus.niuqizp.com/job-vUYNLNzLa.html
A8: 不限专业 | B8: 医疗健康 | C8: 验光师 | D8: 7 | E8: 7 | F8: =IF(E8<2,"证据少",IF(E8<5,"一般","较多")) | G8: 0 | H8: 大专7 | I8: https://campus.niuqizp.com/job-vUk5Mazza.html
A9: 不限专业 | B9: 高级管理 | C9: 管理培训生 | D9: 15 | E9: 6 | F9: =IF(E9<2,"证据少",IF(E9<5,"一般","较多")) | G9: 0 | H9: 本科10、硕士5 | I9: https://campus.niuqizp.com/job-vUlNLNtCN.html
A10: 不限专业 | B10: 教育培训 | C10: 英语教师 | D10: 7 | E10: 6 | F10: =IF(E10<2,"证据少",IF(E10<5,"一般","较多")) | G10: 0 | H10: 本科7 | I10: https://campus.niuqizp.com/job-v8UNLNMCC.html
A11: 不限专业 | B11: 房地产/建筑 | C11: 工程造价 | D11: 6 | E11: 6 | F11: =IF(E11<2,"证据少",IF(E11<5,"一般","较多")) | G11: 0 | H11: 本科4、硕士1、大专1 | I11: https://campus.niuqizp.com/job-vYm5ananM.html
A12: 不限专业 | B12: 医疗健康 | C12: 健康顾问 | D12: 5 | E12: 5 | F12: =IF(E12<2,"证据少",IF(E12<5,"一般","较多")) | G12: 0 | H12: 大专2、未写2、本科1 | I12: https://campus.niuqizp.com/job-v8lNLZazC.html
A13: 不限专业 | B13: 教育培训 | C13: 教师 | D13: 5 | E13: 4 | F13: =IF(E13<2,"证据少",IF(E13<5,"一般","较多")) | G13: 0 | H13: 本科3、字段与正文不一致1、大专1 | I13: https://campus.niuqizp.com/job-v8Y5n5nnC.html
... A893: 马克思主义理论类 | B893: 高级管理 | C893: 管理培训生 | D893: 1 | E893: 1 | F893: =IF(E893<2,"证据少",IF(E893<5,"一般","较多")) | G893: 0 | H893: 硕士1 | I893: https://campus.niuqizp.com/job-vlk5aNa5N.html
